{"resource_state":2,"athlete":{"id":229804,"resource_state":1},"name":"Fractionnés","distance":14318.3,"moving_time":4656,"elapsed_time":4696,"total_elevation_gain":37,"type":"Run","workout_type":0,"id":2891956369,"external_id":"garmin_push_4285585196","upload_id":3072992319,"start_date":"2019-11-26T05:27:50Z","start_date_local":"2019-11-26T06:27:50Z","timezone":"(GMT+01:00) Europe/Paris","utc_offset":3600,"start_latlng":[43.633333,1.437395],"end_latlng":[43.633261,1.437317],"location_city":null,"location_state":null,"location_country":"France","start_latitude":43.633333,"start_longitude":1.437395,"achievement_count":0,"kudos_count":8,"comment_count":0,"athlete_count":2,"photo_count":0,"map":{"id":"a2891956369","summary_polyline":"iciiGuvwGWCGMGE_@A[_@m@GaA@w@_@_AOS@_Ah@m@J}@DOTMhAIfBa@`EYbAOlA]vABjBLnAG`@JVTRR|APjCIb@S`@aBhBOZO|@Cn@Of@Cb@R`@Jb@\\rD^pCH|@Kx@Ud@MFMRWr@SV[ZuBvAsAj@yA\\_AFaCG]DUZCPIl@?d@PbDXjCVlAV`Ad@bAj@^b@HDDAD}@DGHQ@m@IgBEkCUu@AwJq@tCHeCA_AK]@oGk@yAk@qC]{B]Kh@Ez@c@DaFc@k@ScGY`AEfAJ{ADwBImDYcB@e@Yi@?KUSTGn@iB~E?LG`@q@nAClBMjBFXBb@CJMLg@Bc@PaA~Bc@n@eAz@Ob@Dn@j@xEl@zG@IC][wCIa@~@bH_@nCDj@XhBOd@`AtF\\n@FT?JQZWRAHEpBAhDLnAC@?FFRR^Tr@TxBDx@}@^eBZuBj@_@Fe@b@_@d@ENhBx@bDdBb@VaAa@rBbAz@l@|@v@VXBFLDp@h@Z^bBtAh@n@|DpD}@_APL`@p@`CtCxCpBx@X~ACtBJh@Ep@K`Bi@x@Gf@Y`@CmAf@lAm@|AYdD{@dBUnACj@KtBe@f@E|EcA|B[x@ErAW_@NgARMBbBa@v@Gj@Qt@Gl@O|@EbCa@lBEfBWf@B`@K~@?fAK\\{BFaAFa@Co@[yBMi@qCuFgDiGm@y@_@QOA{@Rp@MX?XJZ\\SSm@Ww@Ng@B[g@{BwCmD}DyCyDmBaC_@u@Ga@Qg@Ga@Sq@yBeG@Fl@rAg@sAIg@s@]g@][e@cAiC_AiBmBuE}AiCo@s@m@cA}A{B@DxAlBm@iAk@o@G_@DGd@[X_@LkCh@FjDAfAEhCa@dAItAm@{Az@fAq@ZI^?bD\\hERpGl@bCNxAFjEZ~BX[BaAGTFrBBhBRpADbARNCHcACMy@Qi@B@D^?jATfA?t@a@h@a@zAe@vA[bA]xEsBz@QjCmA_@LkBbArB_ANMT_AEWc@kCW_CCe@GQ]yCeAkGGg@ZdBWcAUwAg@sFESa@{F[qBMuAPxASkB_@SmAb@Q?CEy@uDe@qC?[G]EoB@}AEcABuA^{@XM\\Rn@n@`@RJ@^Qd@i@D_@GYa@u@kAyAEOa@c@s@aAOI","resource_state":2},"trainer":false,"commute":false,"manual":false,"private":false,"visibility":"everyone","flagged":false,"gear_id":"g3745854","from_accepted_tag":false,"upload_id_str":"3072992319","average_speed":3.075,"max_speed":5.8,"average_cadence":85.7,"average_temp":14,"has_heartrate":true,"average_heartrate":135.7,"max_heartrate":168,"heartrate_opt_out":false,"display_hide_heartrate_option":true,"elev_high":150.4,"elev_low":130.4,"pr_count":0,"total_photo_count":0,"has_kudoed":false,"suffer_score":50,"kudos":[{"resource_state":2,"firstname":"Laurent","lastname":"D."},{"resource_state":2,"firstname":"Frédéric","lastname":"L."},{"resource_state":2,"firstname":"Romain","lastname":"D."},{"resource_state":2,"firstname":"Julie","lastname":"D."},{"resource_state":2,"firstname":"Alfred","lastname":"H."},{"resource_state":2,"firstname":"Stijn","lastname":"J."},{"resource_state":2,"firstname":"Noushka","lastname":"D."},{"resource_state":2,"firstname":"Maxence","lastname":"B."}],"laps":[{"id":9519308922,"resource_state":2,"name":"Lap 1","activity":{"id":2891956369,"resource_state":1},"athlete":{"id":229804,"resource_state":1},"elapsed_time":760,"moving_time":726,"start_date":"2019-11-26T05:27:50Z","start_date_local":"2019-11-26T06:27:50Z","distance":2000.61,"start_index":0,"end_index":211,"total_elevation_gain":10,"average_speed":2.76,"max_speed":3.5,"average_cadence":84,"average_heartrate":127.6,"max_heartrate":147,"lap_index":1,"split":1,"pace_zone":1},{"id":9519308923,"resource_state":2,"name":"Lap 2","activity":{"id":2891956369,"resource_state":1},"athlete":{"id":229804,"resource_state":1},"elapsed_time":100,"moving_time":100,"start_date":"2019-11-26T05:40:36Z","start_date_local":"2019-11-26T06:40:36Z","distance":451.26,"start_index":212,"end_index":245,"total_elevation_gain":0,"average_speed":4.51,"max_speed":5.3,"average_cadence":91.6,"average_heartrate":148.2,"max_heartrate":161,"lap_index":2,"split":2,"pace_zone":6},{"id":9519308924,"resource_state":2,"name":"Lap 3","activity":{"id":2891956369,"resource_state":1},"athlete":{"id":229804,"resource_state":1},"elapsed_time":200,"moving_time":200,"start_date":"2019-11-26T05:42:13Z","start_date_local":"2019-11-26T06:42:13Z","distance":539.5,"start_index":246,"end_index":302,"total_elevation_gain":1,"average_speed":2.7,"max_speed":4.4,"average_cadence":83.2,"average_heartrate":127,"max_heartrate":161,"lap_index":3,"split":3,"pace_zone":1},{"id":9519308925,"resource_state":2,"name":"Lap 4","activity":{"id":2891956369,"resource_state":1},"athlete":{"id":229804,"resource_state":1},"elapsed_time":83,"moving_time":83,"start_date":"2019-11-26T05:45:32Z","start_date_local":"2019-11-26T06:45:32Z","distance":386.12,"start_index":303,"end_index":337,"total_elevation_gain":0,"average_speed":4.65,"max_speed":5.4,"average_cadence":92.7,"average_heartrate":152.4,"max_heartrate":164,"lap_index":4,"split":4,"pace_zone":6},{"id":9519308926,"resource_state":2,"name":"Lap 5","activity":{"id":2891956369,"resource_state":1},"athlete":{"id":229804,"resource_state":1},"elapsed_time":266,"moving_time":266,"start_date":"2019-11-26T05:46:58Z","start_date_local":"2019-11-26T06:46:58Z","distance":716.39,"start_index":338,"end_index":417,"total_elevation_gain":0,"average_speed":2.69,"max_speed":5,"average_cadence":82.3,"average_heartrate":124.6,"max_heartrate":163,"lap_index":5,"split":5,"pace_zone":1},{"id":9519308927,"resource_state":2,"name":"Lap 6","activity":{"id":2891956369,"resource_state":1},"athlete":{"id":229804,"resource_state":1},"elapsed_time":103,"moving_time":103,"start_date":"2019-11-26T05:51:24Z","start_date_local":"2019-11-26T06:51:24Z","distance":471.96,"start_index":418,"end_index":470,"total_elevation_gain":0,"average_speed":4.58,"max_speed":5.1,"average_cadence":93.7,"average_heartrate":156.6,"max_heartrate":168,"lap_index":6,"split":6,"pace_zone":6},{"id":9519308929,"resource_state":2,"name":"Lap 7","activity":{"id":2891956369,"resource_state":1},"athlete":{"id":229804,"resource_state":1},"elapsed_time":385,"moving_time":385,"start_date":"2019-11-26T05:53:06Z","start_date_local":"2019-11-26T06:53:06Z","distance":998.23,"start_index":471,"end_index":575,"total_elevation_gain":0,"average_speed":2.59,"max_speed":4.4,"average_cadence":81,"average_heartrate":122.6,"max_heartrate":166,"lap_index":7,"split":7,"pace_zone":1},{"id":9519308930,"resource_state":2,"name":"Lap 8","activity":{"id":2891956369,"resource_state":1},"athlete":{"id":229804,"resource_state":1},"elapsed_time":40,"moving_time":40,"start_date":"2019-11-26T05:59:34Z","start_date_local":"2019-11-26T06:59:34Z","distance":192.74,"start_index":576,"end_index":589,"total_elevation_gain":0,"average_speed":4.82,"max_speed":5.5,"average_cadence":96.7,"average_heartrate":133.1,"max_heartrate":142,"lap_index":8,"split":8,"pace_zone":6},{"id":9519308931,"resource_state":2,"name":"Lap 9","activity":{"id":2891956369,"resource_state":1},"athlete":{"id":229804,"resource_state":1},"elapsed_time":93,"moving_time":93,"start_date":"2019-11-26T06:00:12Z","start_date_local":"2019-11-26T07:00:12Z","distance":240.23,"start_index":590,"end_index":618,"total_elevation_gain":0,"average_speed":2.58,"max_speed":4.6,"average_cadence":82.3,"average_heartrate":140.2,"max_heartrate":157,"lap_index":9,"split":9,"pace_zone":1},{"id":9519308932,"resource_state":2,"name":"Lap 10","activity":{"id":2891956369,"resource_state":1},"athlete":{"id":229804,"resource_state":1},"elapsed_time":59,"moving_time":59,"start_date":"2019-11-26T06:01:47Z","start_date_local":"2019-11-26T07:01:47Z","distance":253.87,"start_index":619,"end_index":639,"total_elevation_gain":1,"average_speed":4.3,"max_speed":5,"average_cadence":95,"average_heartrate":153.4,"max_heartrate":163,"lap_index":10,"split":10,"pace_zone":6},{"id":9519308934,"resource_state":2,"name":"Lap 11","activity":{"id":2891956369,"resource_state":1},"athlete":{"id":229804,"resource_state":1},"elapsed_time":147,"moving_time":147,"start_date":"2019-11-26T06:02:45Z","start_date_local":"2019-11-26T07:02:45Z","distance":370.02,"start_index":640,"end_index":676,"total_elevation_gain":2,"average_speed":2.52,"max_speed":4.7,"average_cadence":82.5,"average_heartrate":135.9,"max_heartrate":166,"lap_index":11,"split":11,"pace_zone":1},{"id":9519308935,"resource_state":2,"name":"Lap 12","activity":{"id":2891956369,"resource_state":1},"athlete":{"id":229804,"resource_state":1},"elapsed_time":57,"moving_time":57,"start_date":"2019-11-26T06:05:14Z","start_date_local":"2019-11-26T07:05:14Z","distance":249.89,"start_index":677,"end_index":705,"total_elevation_gain":0,"average_speed":4.38,"max_speed":5.3,"average_cadence":94.6,"average_heartrate":148.8,"max_heartrate":163,"lap_index":12,"split":12,"pace_zone":6},{"id":9519308936,"resource_state":2,"name":"Lap 13","activity":{"id":2891956369,"resource_state":1},"athlete":{"id":229804,"resource_state":1},"elapsed_time":152,"moving_time":152,"start_date":"2019-11-26T06:06:12Z","start_date_local":"2019-11-26T07:06:12Z","distance":412.27,"start_index":706,"end_index":746,"total_elevation_gain":1,"average_speed":2.71,"max_speed":3.5,"average_cadence":83.1,"average_heartrate":134.4,"max_heartrate":165,"lap_index":13,"split":13,"pace_zone":1},{"id":9519308938,"resource_state":2,"name":"Lap 14","activity":{"id":2891956369,"resource_state":1},"athlete":{"id":229804,"resource_state":1},"elapsed_time":76,"moving_time":76,"start_date":"2019-11-26T06:08:43Z","start_date_local":"2019-11-26T07:08:43Z","distance":346.02,"start_index":747,"end_index":784,"total_elevation_gain":0,"average_speed":4.55,"max_speed":5.5,"average_cadence":94.2,"average_heartrate":153.2,"max_heartrate":168,"lap_index":14,"split":14,"pace_zone":6},{"id":9519308939,"resource_state":2,"name":"Lap 15","activity":{"id":2891956369,"resource_state":1},"athlete":{"id":229804,"resource_state":1},"elapsed_time":314,"moving_time":314,"start_date":"2019-11-26T06:10:00Z","start_date_local":"2019-11-26T07:10:00Z","distance":801.63,"start_index":785,"end_index":870,"total_elevation_gain":2,"average_speed":2.55,"max_speed":3.9,"average_cadence":82.2,"average_heartrate":126.9,"max_heartrate":166,"lap_index":15,"split":15,"pace_zone":1},{"id":9519308940,"resource_state":2,"name":"Lap 16","activity":{"id":2891956369,"resource_state":1},"athlete":{"id":229804,"resource_state":1},"elapsed_time":74,"moving_time":74,"start_date":"2019-11-26T06:15:15Z","start_date_local":"2019-11-26T07:15:15Z","distance":344.02,"start_index":871,"end_index":905,"total_elevation_gain":0,"average_speed":4.65,"max_speed":5.4,"average_cadence":94.1,"average_heartrate":156.1,"max_heartrate":168,"lap_index":16,"split":16,"pace_zone":6},{"id":9519308941,"resource_state":2,"name":"Lap 17","activity":{"id":2891956369,"resource_state":1},"athlete":{"id":229804,"resource_state":1},"elapsed_time":235,"moving_time":235,"start_date":"2019-11-26T06:16:27Z","start_date_local":"2019-11-26T07:16:27Z","distance":609.92,"start_index":906,"end_index":968,"total_elevation_gain":4,"average_speed":2.6,"max_speed":4.6,"average_cadence":82.7,"average_heartrate":132.1,"max_heartrate":168,"lap_index":17,"split":17,"pace_zone":1},{"id":9519308943,"resource_state":2,"name":"Lap 18","activity":{"id":2891956369,"resource_state":1},"athlete":{"id":229804,"resource_state":1},"elapsed_time":42,"moving_time":42,"start_date":"2019-11-26T06:20:23Z","start_date_local":"2019-11-26T07:20:23Z","distance":190.78,"start_index":969,"end_index":985,"total_elevation_gain":0,"average_speed":4.54,"max_speed":5.8,"average_cadence":94.6,"average_heartrate":133,"max_heartrate":143,"lap_index":18,"split":18,"pace_zone":6},{"id":9519308944,"resource_state":2,"name":"Lap 19","activity":{"id":2891956369,"resource_state":1},"athlete":{"id":229804,"resource_state":1},"elapsed_time":121,"moving_time":121,"start_date":"2019-11-26T06:21:05Z","start_date_local":"2019-11-26T07:21:05Z","distance":326.43,"start_index":986,"end_index":1024,"total_elevation_gain":0,"average_speed":2.7,"max_speed":5.6,"average_cadence":83.4,"average_heartrate":136.7,"max_heartrate":158,"lap_index":19,"split":19,"pace_zone":1},{"id":9519308946,"resource_state":2,"name":"Lap 20","activity":{"id":2891956369,"resource_state":1},"athlete":{"id":229804,"resource_state":1},"elapsed_time":75,"moving_time":75,"start_date":"2019-11-26T06:23:06Z","start_date_local":"2019-11-26T07:23:06Z","distance":332.46,"start_index":1025,"end_index":1048,"total_elevation_gain":0,"average_speed":4.43,"max_speed":5,"average_cadence":92.7,"average_heartrate":138.2,"max_heartrate":147,"lap_index":20,"split":20,"pace_zone":6},{"id":9519308948,"resource_state":2,"name":"Lap 21","activity":{"id":2891956369,"resource_state":1},"athlete":{"id":229804,"resource_state":1},"elapsed_time":109,"moving_time":109,"start_date":"2019-11-26T06:24:21Z","start_date_local":"2019-11-26T07:24:21Z","distance":267.85,"start_index":1049,"end_index":1084,"total_elevation_gain":1,"average_speed":2.46,"max_speed":4.7,"average_cadence":83,"average_heartrate":138.4,"max_heartrate":153,"lap_index":21,"split":21,"pace_zone":1},{"id":9519308950,"resource_state":2,"name":"Lap 22","activity":{"id":2891956369,"resource_state":1},"athlete":{"id":229804,"resource_state":1},"elapsed_time":76,"moving_time":76,"start_date":"2019-11-26T06:26:13Z","start_date_local":"2019-11-26T07:26:13Z","distance":310.82,"start_index":1085,"end_index":1110,"total_elevation_gain":2,"average_speed":4.09,"max_speed":5.1,"average_cadence":94,"average_heartrate":155.3,"max_heartrate":163,"lap_index":22,"split":22,"pace_zone":5},{"id":9519308951,"resource_state":2,"name":"Lap 23","activity":{"id":2891956369,"resource_state":1},"athlete":{"id":229804,"resource_state":1},"elapsed_time":182,"moving_time":182,"start_date":"2019-11-26T06:27:32Z","start_date_local":"2019-11-26T07:27:32Z","distance":486.72,"start_index":1111,"end_index":1156,"total_elevation_gain":1,"average_speed":2.67,"max_speed":3.6,"average_cadence":83.6,"average_heartrate":131.7,"max_heartrate":164,"lap_index":23,"split":23,"pace_zone":1},{"id":9519308952,"resource_state":2,"name":"Lap 24","activity":{"id":2891956369,"resource_state":1},"athlete":{"id":229804,"resource_state":1},"elapsed_time":72,"moving_time":72,"start_date":"2019-11-26T06:30:33Z","start_date_local":"2019-11-26T07:30:33Z","distance":303.33,"start_index":1157,"end_index":1180,"total_elevation_gain":1,"average_speed":4.21,"max_speed":4.8,"average_cadence":94.8,"average_heartrate":149.8,"max_heartrate":161,"lap_index":24,"split":24,"pace_zone":6},{"id":9519308953,"resource_state":2,"name":"Lap 25","activity":{"id":2891956369,"resource_state":1},"athlete":{"id":229804,"resource_state":1},"elapsed_time":211,"moving_time":204,"start_date":"2019-11-26T06:31:43Z","start_date_local":"2019-11-26T07:31:43Z","distance":509.48,"start_index":1181,"end_index":1247,"total_elevation_gain":4,"average_speed":2.5,"max_speed":4.5,"average_cadence":83.7,"average_heartrate":131.2,"max_heartrate":161,"lap_index":25,"split":25,"pace_zone":1},{"id":9519308954,"resource_state":2,"name":"Lap 26","activity":{"id":2891956369,"resource_state":1},"athlete":{"id":229804,"resource_state":1},"elapsed_time":112,"moving_time":112,"start_date":"2019-11-26T06:35:14Z","start_date_local":"2019-11-26T07:35:14Z","distance":460.36,"start_index":1248,"end_index":1285,"total_elevation_gain":0,"average_speed":4.11,"max_speed":4.9,"average_cadence":93.6,"average_heartrate":153.7,"max_heartrate":163,"lap_index":26,"split":26,"pace_zone":5},{"id":9519308955,"resource_state":2,"name":"Lap 27","activity":{"id":2891956369,"resource_state":1},"athlete":{"id":229804,"resource_state":1},"elapsed_time":102,"moving_time":102,"start_date":"2019-11-26T06:37:08Z","start_date_local":"2019-11-26T07:37:08Z","distance":257.5,"start_index":1286,"end_index":1313,"total_elevation_gain":1,"average_speed":2.52,"max_speed":3,"average_cadence":83.1,"average_heartrate":137.3,"max_heartrate":162,"lap_index":27,"split":27,"pace_zone":1},{"id":9519308956,"resource_state":2,"name":"Lap 28","activity":{"id":2891956369,"resource_state":1},"athlete":{"id":229804,"resource_state":1},"elapsed_time":57,"moving_time":57,"start_date":"2019-11-26T06:38:50Z","start_date_local":"2019-11-26T07:38:50Z","distance":232.77,"start_index":1314,"end_index":1335,"total_elevation_gain":0,"average_speed":4.08,"max_speed":4.9,"average_cadence":91.8,"average_heartrate":147.7,"max_heartrate":159,"lap_index":28,"split":28,"pace_zone":5},{"id":9519308957,"resource_state":2,"name":"Lap 29","activity":{"id":2891956369,"resource_state":1},"athlete":{"id":229804,"resource_state":1},"elapsed_time":88,"moving_time":88,"start_date":"2019-11-26T06:39:49Z","start_date_local":"2019-11-26T07:39:49Z","distance":222.39,"start_index":1336,"end_index":1359,"total_elevation_gain":1,"average_speed":2.53,"max_speed":3.9,"average_cadence":83.8,"average_heartrate":140.7,"max_heartrate":159,"lap_index":29,"split":29,"pace_zone":1},{"id":9519308958,"resource_state":2,"name":"Lap 30","activity":{"id":2891956369,"resource_state":1},"athlete":{"id":229804,"resource_state":1},"elapsed_time":48,"moving_time":48,"start_date":"2019-11-26T06:41:18Z","start_date_local":"2019-11-26T07:41:18Z","distance":180.46,"start_index":1360,"end_index":1378,"total_elevation_gain":2,"average_speed":3.76,"max_speed":4.6,"average_cadence":91.3,"average_heartrate":148.8,"max_heartrate":155,"lap_index":30,"split":30,"pace_zone":4},{"id":9519308959,"resource_state":2,"name":"Lap 31","activity":{"id":2891956369,"resource_state":1},"athlete":{"id":229804,"resource_state":1},"elapsed_time":55,"moving_time":55,"start_date":"2019-11-26T06:42:06Z","start_date_local":"2019-11-26T07:42:06Z","distance":152.79,"start_index":1379,"end_index":1395,"total_elevation_gain":0,"average_speed":2.78,"max_speed":3.8,"average_cadence":84.1,"average_heartrate":149.8,"max_heartrate":158,"lap_index":31,"split":31,"pace_zone":1},{"id":9519308961,"resource_state":2,"name":"Lap 32","activity":{"id":2891956369,"resource_state":1},"athlete":{"id":229804,"resource_state":1},"elapsed_time":34,"moving_time":34,"start_date":"2019-11-26T06:43:00Z","start_date_local":"2019-11-26T07:43:00Z","distance":132.58,"start_index":1396,"end_index":1408,"total_elevation_gain":0,"average_speed":3.9,"max_speed":4.7,"average_cadence":93.4,"average_heartrate":149.3,"max_heartrate":154,"lap_index":32,"split":32,"pace_zone":4},{"id":9519308962,"resource_state":2,"name":"Lap 33","activity":{"id":2891956369,"resource_state":1},"athlete":{"id":229804,"resource_state":1},"elapsed_time":41,"moving_time":41,"start_date":"2019-11-26T06:43:37Z","start_date_local":"2019-11-26T07:43:37Z","distance":111.99,"start_index":1409,"end_index":1418,"total_elevation_gain":0,"average_speed":2.73,"max_speed":3.2,"average_cadence":83.9,"average_heartrate":152.9,"max_heartrate":157,"lap_index":33,"split":33,"pace_zone":1},{"id":9519308963,"resource_state":2,"name":"Lap 34","activity":{"id":2891956369,"resource_state":1},"athlete":{"id":229804,"resource_state":1},"elapsed_time":111,"moving_time":111,"start_date":"2019-11-26T06:44:18Z","start_date_local":"2019-11-26T07:44:18Z","distance":455.48,"start_index":1419,"end_index":1452,"total_elevation_gain":0,"average_speed":4.1,"max_speed":4.7,"average_cadence":93.6,"average_heartrate":157.5,"max_heartrate":161,"lap_index":34,"split":34,"pace_zone":5}],"photos":[],"streams":{"altitude":[138,137.6,137.6,137.6,137.6,137.6,137.8,137.8,138,138,138,138.2,138.4,138.4,138.6,138.6,138.6,138.8,139,139.2,139.2,139.2,139.4,139.4,139.4,139.6,139.8,140,140.2,140.6,140.8,140.8,140.6,140.2,140.2,140.4,140.8,140.8,141,141.2,141.2,141.2,141.2,141.4,141.6,141.8,142,142.2,142.4,142.4,142.4,142.6,142.6,143,143,143,143.2,143.2,143.2,143.2,143.4,143.4,143.6,143.8,143.8,143.6,144,144,144,144.2,144.2,144.2,144.2,144.2,144.4,144.4,144.4,143.8,144.2,144.4,144.4,144.8,144.8,144.8,144.8,144.6,144.4,144.6,144.6,144.6,144.6,144.6,144.6,144.6,144.8,144.8,145,145.2,145.2,145.4,145.4,145.4,145.4,145.6,145.6,145.8,145.8,145.6,145.6,146,146,146,145.8,145.8,145.6,145.6,145.6,145.2,145.2,144.8,144.4,144.4,144.4,144,143.8,143.4,143.4,143.2,143.2,143,142.8,142.8,142.8,142.8,141.6,141.8,142.6,142.4,142.4,142.4,142.6,142.6,142.6,142.6,142.6,142.8,142.8,142.8,142.8,143,143.2,143,142.8,143,143,143,143,142.8,142.8,142.6,142.8,142.8,142.6,142.8,142.6,142.6,142.6,142.6,142.6,142.6,142.8,142.8,142.8,143,143,143,143,143,143,143,143,143,143,143,143,143,143,143,143.2,143.2,143.4,143.2,142.8,142.8,143,143,142.8,143,143,143,143,143,143.8,144,144.2,144.4,144.4,144.8,144.8,145,145.2,145.2,145,144.8,144.4,144.4,145,145,144.8,144.8,144.4,144.6,144.8,144.4,144.4,144.6,144.6,144.2,144.2,144.2,144.4,144.4,144.2,144.4,144.6,144.6,144.2,144,143.8,144.2,144,143.8,143.2,143.4,143.4,143.4,143.2,143.2,143.2,143.2,143.2,144,144,144,144.2,144.2,144.2,144,144,143.6,143.6,143.8,143.8,144,143.8,143.8,143.8,143.6,143.6,143.6,143.6,143.6,143.4,143.2,143.2,143.2,143.2,143.2,143.2,143.2,143,142.4,142.2,142,141.6,141.8,141.8,141.8,142,142.2,142.2,142.2,142.4,142.8,143,143.2,143.2,143.2,143.4,143.6,143.8,144,143.8,143.8,143.4,142,141.2,140.4,140.4,140.4,140.2,140,140,140.2,140.2,140.2,140.2,140.2,140,140,140,140,140,140.2,140.2,140.2,140.2,140.2,140.2,140.2,140.6,140.4,140.2,139.6,139.8,139.8,140,139.8,140.2,140.2,140.2,141,140.4,139.6,139.6,139.6,139.4,139.6,139.6,139.8,139.8,139.8,139.8,139.8,139.8,139.8,139.8,139.8,139.8,139.6,139.6,139.6,139.4,139.4,139.4,139.4,139.2,139.2,139.2,139,139,139,139,139.2,139.2,139.4,139.2,139.4,139.2,139.2,139.2,139,139,138.4,138.2,137.8,137.4,137.2,136.8,136.6,136.4,136,135.6,135.6,135.8,135.8,135.8,135.2,135.2,135.2,135.2,135.2,135.4,135.4,135.4,135.4,135.4,135.4,135.4,135.2,135.4,135.2,135.2,135,135,134.8,134.6,134.4,134.4,134.4,134.4,134.4,134.4,134.4,134.4,134.4,134.6,134.6,134.6,134.6,134.4,134.2,134.2,134.2,134.2,134.2,134.2,134.2,134.2,134.4,134.2,134.2,134.2,134.2,134.4,134.4,134.4,134.4,134.4,134.4,134.4,134.2,134.2,134.4,134.4,134.6,134.6,134.6,134.4,134.4,134.4,134.2,134.2,134.2,134.4,134.4,134.8,135,134.4,134.6,134.6,134.8,134.6,134.6,135,135.2,134.8,135.2,135.2,135,135,135.2,135.2,135,135,135,135,135.4,135.4,135.4,135.2,135.2,135.4,135.4,135.2,135,135.4,135.6,135.6,135.6,135.6,135.6,135.6,135.4,135.6,135.6,135.6,135.6,135.6,135.4,135.4,135.2,135.2,135.2,135.2,135,135,135,134.8,135,135,135.2,135.4,135.4,135.4,135.6,135.4,135.2,135.2,135,135,135,135,134.8,134.8,134.8,134.8,134.6,134.6,134.8,135,135,134.4,134,133.2,133,133,132.8,132.2,131.8,131.8,131.4,131.6,131.8,132,132.2,132.4,132.4,132.4,132.4,132.4,132.4,132.2,132.4,132.4,132.4,132.6,132.4,132.2,132.2,132.2,132.2,132.2,132.2,132.2,132.2,132.2,132,132,131.8,132,131.8,131.6,131.4,130.8,130.8,130.6,130.6,130.6,130.6,130.6,130.6,130.6,130.6,130.6,130.6,130.4,130.4,130.8,131,131,131,131.4,131.2,131.2,131.2,131,131,131,130.8,130.8,130.8,130.8,131,131,131,131.2,131.2,131,131,131,130.8,130.8,130.6,130.8,130.8,130.8,131,131.2,131.6,131.8,132.2,132.6,132.8,132.8,132.8,132.6,132.4,132.4,132.4,132.6,132.4,132.4,132.6,132.8,133,133,133.2,133.2,133.2,133.2,133.4,133.4,133.2,133.2,133.6,133.8,134.2,134.2,134.2,134.4,134.4,134.6,134.6,134.4,134.2,134.2,134.2,134.6,134.6,134.6,134.6,134.2,134.2,134.4,134.6,134.6,134.4,134.4,134.2,134.2,134.6,134.6,134.8,135,135,135.2,135.4,135.2,135.2,135.4,135.4,135.4,135.2,135,135,135.2,135.2,135,135.2,135,135,135,135,135,134.8,134.6,134.6,134.8,135,135,135.4,135.6,135.4,135.4,135.4,135.4,135.6,135.8,135.6,135.4,135.6,135.6,135.6,135.6,135.6,135.6,135.4,135.6,135.6,135.4,135.4,135.4,135.2,135.2,135.2,135,134.8,134.8,134.8,134.8,135,134.8,135,134.4,134.4,134.4,134.4,134.6,134.8,134.8,134.6,134.6,134.8,134.8,134.8,134.8,134.8,134.8,134.6,134.8,134.6,134.6,134.6,134.6,134.4,134.4,134.4,134.6,134.6,134.4,134.4,134.4,134.4,134.2,134,134.2,134.2,134.2,134.2,134.2,134.2,134.2,134.2,134.2,134.2,134.4,134.4,134.2,133.8,133.8,134,134.4,134.4,134.6,134.4,134.4,134.4,134.4,134.8,134.8,134.8,134.8,134.8,134.6,134.4,134.2,134.2,134.2,134.4,134.8,134.8,134.8,134.6,134.8,134.8,135,134.8,134,134,133.8,133.6,133.4,133.4,133.4,133.4,133.6,133.6,133.6,133.6,133.6,133.6,133.6,133.6,133.6,133.4,133.4,133.4,133.4,133.6,133.6,133.6,133.8,134.2,135,135.6,135.8,136,136.2,136.2,136.2,136.2,136.4,136.6,136.8,136.8,136.4,136.2,136,136,136,136.2,136.6,136.8,136.8,136.8,136.8,136.8,136.2,136.2,136.2,136.4,136.4,136.4,136.6,136.8,136.8,136.6,136.6,136.6,136.4,136.6,136.4,136.4,136.2,136.2,136.2,135.8,135.8,135.8,135.6,135.6,135.4,135.4,135.2,135.2,135,135.2,135.2,135.2,135,135,134.8,135,135,135.2,135.6,135.6,135.6,135.6,135.4,135.4,135.4,135.6,135.8,135.8,135.8,136,136,135.8,135.6,135.6,136,136.2,136.2,136.4,136.6,136.6,136.8,137,137.2,137.2,137.4,137.6,137.8,137.8,138.2,138.2,138.4,138.6,138.8,139.2,139.2,139.2,139.4,139.4,139.4,139.6,139.8,139.8,139.8,140,140.4,140.6,140.6,140.4,140.2,140,139.8,139.8,139.6,139.4,139.6,139.4,139.4,139.2,139,138.8,138.8,138.8,138.8,138.8,139,139,139.2,139.2,139.2,139.2,139.6,140,140.2,140,140.2,140.2,139.8,139.6,139.6,139.4,139.4,139.8,140,140,140,140.2,140.2,140.2,140,139.8,139.6,139.6,139.6,139.6,139.6,139.8,139.8,139.8,140,140,140,140,140.2,139.8,140,140,139.8,139.8,139.6,139.8,139.8,139.6,139.4,139.4,139.2,139.2,139,139,138.8,138.6,138.8,138.6,138.6,138.6,138.6,138.8,138.8,138.8,138.4,138.2,138.2,138.2,138,138.2,138.4,138.4,138.4,138.2,138.2,138.2,138.2,138,138,137.8,137.8,138,137.8,137.8,137.8,137.8,137.8,138,138,137.8,137.8,137.8,137.8,137.6,137.4,137.4,137.4,137.4,137.4,137.4,137.6,137.8,137.8,137.8,138.2,138.4,139.2,139.4,140,140.2,140.4,140.6,140.6,140.6,140.6,140.8,141.2,141.4,141.6,141.6,141.4,141.4,141.4,141.6,141.6,141.6,141.8,141.8,141.8,142,142,141.8,141.8,142,142,141.6,141.8,142.2,142.2,142,142,141.8,141.8,142,141.8,142,142,142.2,142.2,141.8,141.8,142.2,142.2,142.4,142.4,142.6,142.6,142.6,142.4,142.6,143,143,143,143,143.2,143.2,143,143.2,143.4,143.4,143.4,143.4,143.2,143.2,143.2,143.2,143.2,143.4,143.4,143.4,143.6,143.4,143.4,143.4,143.4,143.4,143.4,143.6,143.8,143.8,143.8,143.8,143.8,143.8,144,144,144,144,144.2,144.2,144.4,144.4,144.4,144.6,144.6,144.4,144.6,144.6,144.6,144.6,144.6,144.6,144.6,144.8,144.8,144.8,144.8,144.4,144.4,144.4,144.6,144.6,144.6,144.6,144.6,144.8,144.8,144.8,144.8,144.8,144.8,144.8,145.4,145.6,145.6,146.6,147.8,148,148.4,148.6,148.4,148.2,147.6,147,146.8,146.6,145.8,145.6,145.6,145.4,145,145,144.8,144.6,144.6,144.6,144.4,144.2,144.2,144,144,144.2,144.2,144.4,144.4,144.6,145,145,144.8,144.8,144.8,144.6,144.4,144.4,144.4,144.6,144.6,144.6,144.6,144.6,144.4,144.4,144.4,144.4,144.4,144.6,144.6,144.6,144.4,144.4,144.6,144.8,144.8,145,144.8,144.8,145,145,145.2,145.2,145.2,145.4,145.4,145.2,145.4,145.4,145.4,145.4,145.2,145.4,145.4,145.4,145.4,145.4,145.4,145.6,145.6,145.6,145.4,145.2,145.4,145.6,145.6,145.6,145.6,145.4,145.4,145.6,145.6,146,146,146,146,146,146,146.2,146,146,146.2,146.2,146.2,146.2,146.2,146.2,146.2,146.2,146,146,146,146,146.2,146.4,146,145.8,145.8,146,145.8,145.8,146.2,146,145.8,145.8,145.8,146,146,146,146,145.6,145.6,146,146.2,146.2,146.2,146.4,146.2,146.2,146.2,146.2,146.4,146.4,146.6,147,147.2,147.4,147.8,148,148.4,148.6,148.6,148.8,148.8,149.2,149.2,149,149,149.2,149.2,149.2,149.4,149.4,149.6,149.6,149.6,149.6,149.8,149.8,149.8,149.8,149.8,149.8,149.8,150,149.8,150,150,150,150.2,150.2,150.2,150.2,150.2,150.2,150.2,150.2,150.2,150.2,150.2,150.2,150.2,150.2,150.4,150.2,150.2,149.8,149.4,149.4,149.4,149.4,149.4,149.6,149.8,149.8,149.4,149.6,149.6,149.4,149.2,149,149,148.8,148.8,149.2,149.2,149.2,149.2,149.2,149.2,149.6,149.6,149.6,149.4,149.6,149.6,149.6,149.6,149.8,150,149.8,150,150.2,150.2,150.2,150.4,150.4,150.4,150.2,150,150,150,150,150],"latlng":[[43.633333,1.437395],[43.633391,1.437399],[43.633411,1.437395],[43.633456,1.437412],[43.633465,1.437428],[43.633492,1.437487],[43.633534,1.437511],[43.633553,1.437513],[43.633669,1.437514],[43.633699,1.437528],[43.633723,1.43755],[43.63376,1.437596],[43.63382,1.43767],[43.633837,1.43768],[43.633965,1.437699],[43.634045,1.437724],[43.634061,1.437729],[43.634175,1.437736],[43.634249,1.437716],[43.63429,1.437703],[43.634309,1.437703],[43.634393,1.437717],[43.634467,1.437765],[43.634551,1.437816],[43.63467,1.437878],[43.634844,1.437919],[43.634915,1.437936],[43.634991,1.437954],[43.635017,1.437954],[43.635091,1.437941],[43.635232,1.437849],[43.635301,1.437803],[43.635417,1.437736],[43.635519,1.437711],[43.63564,1.437673],[43.635759,1.437657],[43.635905,1.437654],[43.635952,1.437645],[43.636034,1.437535],[43.636046,1.437408],[43.636059,1.437346],[43.636077,1.437291],[43.636084,1.437263],[43.636105,1.43716],[43.636122,1.436958],[43.636138,1.436859],[43.636146,1.436728],[43.636157,1.43664],[43.63617,1.436578],[43.636187,1.436452],[43.63621,1.436358],[43.636245,1.436179],[43.636254,1.436114],[43.636284,1.435923],[43.63632,1.435754],[43.636328,1.435671],[43.636365,1.435564],[43.636431,1.435393],[43.636443,1.435362],[43.636453,1.435331],[43.636504,1.435142],[43.636505,1.43511],[43.636536,1.434945],[43.636613,1.434756],[43.636624,1.43472],[43.636634,1.434683],[43.636665,1.434579],[43.636688,1.434509],[43.636686,1.434315],[43.636687,1.43428],[43.636658,1.434066],[43.636661,1.43396],[43.636638,1.433878],[43.636632,1.433773],[43.636595,1.433564],[43.636622,1.433433],[43.63663,1.43339],[43.636574,1.433277],[43.636466,1.433175],[43.636419,1.432987],[43.636412,1.43295],[43.636372,1.432747],[43.636365,1.432708],[43.63635,1.432599],[43.636319,1.432391],[43.63631,1.432279],[43.63628,1.432111],[43.636277,1.432076],[43.636279,1.432006],[43.63631,1.431859],[43.636323,1.431826],[43.636428,1.431656],[43.63645,1.431631],[43.636518,1.431557],[43.636651,1.431429],[43.636672,1.431407],[43.636752,1.431309],[43.636832,1.431211],[43.636912,1.43112],[43.636993,1.43098],[43.637049,1.430776],[43.637059,1.430744],[43.637075,1.430677],[43.637098,1.430471],[43.637099,1.430436],[43.637172,1.430239],[43.637191,1.430052],[43.637113,1.429903],[43.637096,1.42988],[43.637037,1.429703],[43.637031,1.429674],[43.63702,1.429613],[43.63701,1.42957],[43.637009,1.429558],[43.636992,1.429437],[43.636981,1.429367],[43.636944,1.429204],[43.636908,1.429013],[43.636903,1.428981],[43.63688,1.428801],[43.636836,1.428622],[43.636826,1.428588],[43.636811,1.428486],[43.636783,1.428358],[43.636771,1.428283],[43.636725,1.428076],[43.63672,1.428043],[43.636696,1.427909],[43.636674,1.427762],[43.636677,1.427727],[43.636721,1.427514],[43.636732,1.427479],[43.636756,1.427424],[43.636843,1.427287],[43.636915,1.427249],[43.636921,1.42724],[43.636989,1.42714],[43.637085,1.42692],[43.6371,1.426887],[43.637208,1.426761],[43.637349,1.426625],[43.637402,1.426586],[43.637556,1.42647],[43.63758,1.426451],[43.637685,1.426378],[43.637778,1.426304],[43.637931,1.426187],[43.637986,1.426159],[43.638036,1.426129],[43.638185,1.426049],[43.638259,1.426015],[43.638281,1.426],[43.638358,1.425963],[43.638512,1.425899],[43.638595,1.425868],[43.638749,1.425823],[43.6388,1.425812],[43.638965,1.425789],[43.639018,1.425783],[43.639126,1.425779],[43.639276,1.42579],[43.639429,1.425796],[43.639533,1.425792],[43.639698,1.425806],[43.639772,1.42581],[43.639921,1.42578],[43.639963,1.425747],[43.640034,1.425647],[43.640058,1.425554],[43.64009,1.42535],[43.640101,1.425322],[43.640107,1.425133],[43.640096,1.42508],[43.640067,1.424888],[43.640059,1.424818],[43.640048,1.424614],[43.640034,1.424508],[43.640011,1.42431],[43.640002,1.424244],[43.639982,1.424153],[43.639955,1.423991],[43.639917,1.423803],[43.639906,1.423737],[43.639886,1.423614],[43.639827,1.423427],[43.639819,1.423397],[43.639765,1.423222],[43.639755,1.423192],[43.639692,1.42301],[43.639647,1.422891],[43.639565,1.422728],[43.639551,1.4227],[43.639458,1.422555],[43.639434,1.422533],[43.639296,1.422435],[43.639239,1.422392],[43.639147,1.422371],[43.639059,1.422342],[43.639025,1.422317],[43.639034,1.422283],[43.639051,1.422273],[43.639126,1.422273],[43.63925,1.422258],[43.639344,1.422258],[43.639358,1.422248],[43.639374,1.422216],[43.639388,1.422205],[43.639474,1.422199],[43.639499,1.422204],[43.639649,1.422224],[43.639678,1.42224],[43.639708,1.422249],[43.639894,1.422253],[43.640086,1.42227],[43.640225,1.422272],[43.640442,1.422302],[43.640618,1.422325],[43.640792,1.422354],[43.640883,1.422379],[43.640928,1.422385],[43.641062,1.42239],[43.641106,1.422389],[43.641193,1.422393],[43.641402,1.422423],[43.641524,1.42245],[43.641735,1.422459],[43.641814,1.422468],[43.642021,1.422503],[43.642174,1.422529],[43.642213,1.422531],[43.642292,1.422541],[43.6425,1.422557],[43.642665,1.422571],[43.642851,1.42261],[43.642932,1.422623],[43.64307,1.422642],[43.643075,1.422641],[43.643039,1.422636],[43.642965,1.422638],[43.642783,1.422639],[43.642651,1.422626],[43.642567,1.422619],[43.642523,1.422615],[43.64248,1.42261],[43.642433,1.422606],[43.642391,1.422601],[43.642325,1.422594],[43.642326,1.422594],[43.642349,1.422588],[43.642507,1.422592],[43.642649,1.422595],[43.642746,1.4226],[43.642792,1.422597],[43.642936,1.422601],[43.642992,1.422603],[43.643041,1.422615],[43.643182,1.422645],[43.643207,1.422645],[43.643254,1.422652],[43.643319,1.422666],[43.643362,1.422667],[43.643463,1.422659],[43.64354,1.422672],[43.643565,1.422679],[43.643703,1.422707],[43.643726,1.422708],[43.643774,1.422713],[43.64382,1.422718],[43.643875,1.422736],[43.644022,1.42275],[43.644075,1.422753],[43.644177,1.422782],[43.644255,1.422797],[43.644428,1.42281],[43.644499,1.422822],[43.644563,1.422827],[43.644672,1.422852],[43.644824,1.422871],[43.644921,1.422911],[43.645072,1.422978],[43.645142,1.42302],[43.645222,1.423074],[43.645238,1.423081],[43.645277,1.423093],[43.645408,1.423116],[43.645559,1.423145],[43.645655,1.423182],[43.645786,1.423207],[43.645856,1.423207],[43.646,1.423241],[43.646105,1.423281],[43.646238,1.423314],[43.646327,1.42335],[43.646434,1.423371],[43.646536,1.423383],[43.64662,1.423398],[43.64663,1.423379],[43.646639,1.423356],[43.646684,1.423187],[43.646688,1.423156],[43.6467,1.423064],[43.646711,1.422906],[43.646718,1.422881],[43.64673,1.422867],[43.646781,1.422864],[43.646893,1.422851],[43.646945,1.422858],[43.647034,1.422868],[43.647169,1.422887],[43.647253,1.422902],[43.647336,1.422914],[43.647547,1.422949],[43.647684,1.42297],[43.647737,1.422983],[43.647815,1.423005],[43.647858,1.423012],[43.648025,1.423038],[43.648098,1.423074],[43.648139,1.423101],[43.648178,1.42312],[43.648247,1.423138],[43.648289,1.423138],[43.648327,1.423137],[43.648483,1.423159],[43.648596,1.423183],[43.648635,1.423185],[43.648756,1.423184],[43.648854,1.423185],[43.64907,1.423216],[43.649289,1.42323],[43.649458,1.423246],[43.649534,1.423268],[43.649549,1.423261],[43.649401,1.423283],[43.64921,1.423293],[43.649161,1.423275],[43.649063,1.423254],[43.64892,1.42324],[43.648855,1.423239],[43.64886,1.423243],[43.648893,1.423232],[43.649025,1.423241],[43.649162,1.423229],[43.64925,1.423209],[43.64931,1.423206],[43.649414,1.423224],[43.649572,1.423237],[43.649621,1.423242],[43.649685,1.423235],[43.649779,1.423246],[43.649802,1.423249],[43.64991,1.42325],[43.650026,1.423268],[43.650133,1.423285],[43.650234,1.423292],[43.650348,1.423319],[43.650411,1.423333],[43.65044,1.423342],[43.650543,1.423349],[43.650614,1.423359],[43.650635,1.423359],[43.650741,1.423366],[43.650787,1.423385],[43.650809,1.423382],[43.650874,1.423379],[43.651029,1.423383],[43.651052,1.423381],[43.651078,1.423378],[43.651216,1.423378],[43.651287,1.423371],[43.651419,1.423452],[43.65143,1.423475],[43.651473,1.423504],[43.651516,1.423513],[43.651537,1.42351],[43.6516,1.423508],[43.651681,1.423506],[43.651735,1.423598],[43.651742,1.423614],[43.651775,1.423574],[43.65179,1.423564],[43.651845,1.423509],[43.651854,1.423482],[43.651879,1.423304],[43.651889,1.42326],[43.651981,1.423082],[43.652034,1.422945],[43.652055,1.422907],[43.652094,1.422819],[43.652147,1.422715],[43.652189,1.422629],[43.652256,1.422481],[43.652341,1.422317],[43.652417,1.422142],[43.652411,1.422074],[43.652444,1.421938],[43.652456,1.421908],[43.652541,1.421753],[43.652576,1.421703],[43.652684,1.421562],[43.652701,1.421509],[43.652721,1.421321],[43.652731,1.421142],[43.652728,1.420954],[43.652731,1.420922],[43.652749,1.420722],[43.652754,1.420661],[43.652789,1.420471],[43.652798,1.42041],[43.652754,1.420285],[43.652737,1.420106],[43.65275,1.420048],[43.652829,1.419972],[43.652888,1.419966],[43.65302,1.419952],[43.653129,1.419919],[43.653186,1.419878],[43.653202,1.419864],[43.653234,1.419821],[43.653288,1.419727],[43.653332,1.419632],[43.653379,1.419528],[43.653428,1.419427],[43.653454,1.419376],[43.653505,1.41928],[43.653536,1.419228],[43.65359,1.419156],[43.653628,1.419103],[43.65366,1.419058],[43.653717,1.418988],[43.653789,1.418916],[43.653831,1.418886],[43.653874,1.418857],[43.653911,1.418825],[43.653952,1.41879],[43.654061,1.418685],[43.654091,1.418646],[43.654131,1.41856],[43.65414,1.418508],[43.65414,1.418449],[43.654113,1.41826],[43.654102,1.418202],[43.654048,1.417918],[43.654036,1.417862],[43.653985,1.417615],[43.65394,1.417399],[43.653897,1.417171],[43.653892,1.41711],[43.653885,1.417048],[43.653876,1.416985],[43.653868,1.416923],[43.653857,1.41686],[43.653837,1.416804],[43.653814,1.416694],[43.65378,1.416402],[43.653751,1.416233],[43.653698,1.41594],[43.65369,1.415894],[43.653679,1.415838],[43.653663,1.415753],[43.653654,1.415746],[43.653651,1.415803],[43.653665,1.415901],[43.653674,1.415957],[43.653686,1.416015],[43.653698,1.416076],[43.653731,1.41626],[43.653783,1.416549],[43.653816,1.416711],[43.653828,1.416768],[43.653842,1.416818],[43.653854,1.416861],[43.653868,1.416883],[43.653831,1.416737],[43.653793,1.416538],[43.653773,1.416467],[43.653734,1.416317],[43.653704,1.416159],[43.653683,1.416067],[43.653642,1.41588],[43.653621,1.415747],[43.653596,1.415625],[43.653591,1.415594],[43.653541,1.415427],[43.653567,1.415299],[43.653581,1.415229],[43.653594,1.415165],[43.653642,1.414986],[43.653658,1.414927],[43.653696,1.41477],[43.653702,1.414701],[43.653688,1.414578],[43.65367,1.414483],[43.653621,1.414301],[43.653604,1.414202],[43.653577,1.414109],[43.653542,1.413952],[43.653609,1.413813],[43.653625,1.41376],[43.653616,1.413706],[43.653566,1.413529],[43.653543,1.41344],[43.653482,1.413262],[43.65346,1.413177],[43.653409,1.412999],[43.653389,1.412907],[43.653336,1.412726],[43.653321,1.412661],[43.653293,1.41253],[43.653241,1.412436],[43.653147,1.412296],[43.653139,1.412268],[43.653109,1.412182],[43.653106,1.412125],[43.653198,1.411983],[43.65331,1.411885],[43.65332,1.411836],[43.653329,1.411643],[43.653334,1.411549],[43.65335,1.411363],[43.653355,1.411264],[43.653349,1.411089],[43.653352,1.410994],[43.653366,1.410808],[43.653367,1.410776],[43.653372,1.410575],[43.653364,1.410413],[43.653337,1.410219],[43.653323,1.410148],[43.653291,1.41001],[43.653298,1.410012],[43.653308,1.410009],[43.653314,1.41],[43.65332,1.409978],[43.653319,1.409961],[43.653279,1.409861],[43.653269,1.409849],[43.653236,1.409811],[43.653222,1.409795],[43.65317,1.409708],[43.653094,1.409541],[43.653069,1.409445],[43.653048,1.409347],[43.653036,1.409281],[43.653006,1.409108],[43.652983,1.40896],[43.652974,1.408929],[43.652956,1.408832],[43.652922,1.408614],[43.652925,1.408544],[43.652942,1.408519],[43.653064,1.408455],[43.653211,1.408401],[43.653234,1.408389],[43.653378,1.408344],[43.653425,1.408331],[43.653572,1.408289],[43.653595,1.408282],[43.65374,1.408243],[43.653785,1.408225],[43.653926,1.408169],[43.653998,1.408146],[43.654144,1.408106],[43.654191,1.408085],[43.65433,1.40802],[43.654354,1.408021],[43.654498,1.407987],[43.654565,1.407936],[43.654685,1.407806],[43.654734,1.407736],[43.654845,1.40761],[43.654877,1.407532],[43.654868,1.407517],[43.654851,1.407502],[43.654751,1.407456],[43.654688,1.407418],[43.654572,1.407357],[43.654532,1.407334],[43.654346,1.407241],[43.654212,1.407156],[43.654172,1.407128],[43.654,1.407021],[43.653866,1.406937],[43.653819,1.406914],[43.653684,1.406826],[43.653521,1.406731],[43.653346,1.406613],[43.653352,1.406608],[43.653533,1.406693],[43.653626,1.406755],[43.653657,1.406777],[43.653675,1.406789],[43.653566,1.406731],[43.653543,1.406717],[43.653519,1.406705],[43.653399,1.406624],[43.653285,1.406563],[43.653225,1.406524],[43.653093,1.406442],[43.653027,1.406397],[43.652901,1.406295],[43.652798,1.406214],[43.652719,1.406146],[43.652635,1.40607],[43.652611,1.40605],[43.652589,1.406028],[43.652481,1.40593],[43.652402,1.405847],[43.652384,1.405831],[43.652363,1.405809],[43.652361,1.405796],[43.652359,1.405787],[43.652348,1.405767],[43.652277,1.405737],[43.652148,1.405626],[43.652125,1.405607],[43.652023,1.405524],[43.651983,1.405486],[43.651883,1.405367],[43.651796,1.405291],[43.651654,1.405174],[43.651586,1.40512],[43.651551,1.40509],[43.651382,1.404935],[43.651312,1.404859],[43.651273,1.404814],[43.651173,1.404698],[43.651105,1.404633],[43.650931,1.404465],[43.650763,1.404304],[43.650688,1.404243],[43.650581,1.404145],[43.650447,1.404013],[43.650375,1.403948],[43.650331,1.403912],[43.6503,1.403879],[43.650227,1.403801],[43.65026,1.403834],[43.650387,1.403982],[43.650461,1.40406],[43.650524,1.404122],[43.650536,1.404129],[43.650534,1.404126],[43.650448,1.404054],[43.650439,1.404031],[43.650353,1.403923],[43.650276,1.403808],[43.650179,1.403696],[43.650165,1.403676],[43.650083,1.403601],[43.650068,1.403578],[43.649959,1.403454],[43.649941,1.403431],[43.649874,1.403337],[43.649774,1.403217],[43.649662,1.403095],[43.649622,1.403058],[43.64956,1.403005],[43.649432,1.402908],[43.649414,1.402901],[43.64929,1.402821],[43.649248,1.40278],[43.649116,1.402668],[43.64907,1.40264],[43.648935,1.402545],[43.648855,1.402481],[43.648734,1.402413],[43.648696,1.4024],[43.648563,1.402353],[43.648467,1.402343],[43.64832,1.402358],[43.648219,1.402356],[43.64808,1.402376],[43.647983,1.402371],[43.647856,1.402365],[43.647758,1.402345],[43.647734,1.402344],[43.647631,1.402334],[43.647584,1.402328],[43.647497,1.402319],[43.647455,1.402322],[43.647381,1.40233],[43.647281,1.402341],[43.647106,1.402384],[43.64707,1.402392],[43.647032,1.402406],[43.646993,1.402422],[43.646951,1.402439],[43.646903,1.40246],[43.646829,1.402503],[43.646671,1.40257],[43.646588,1.402595],[43.646549,1.402611],[43.646478,1.402623],[43.6464,1.40263],[43.646253,1.402659],[43.646131,1.40274],[43.646053,1.402781],[43.645991,1.4028],[43.645946,1.402803],[43.645905,1.402807],[43.645883,1.402809],[43.645883,1.402803],[43.645996,1.40274],[43.646132,1.402673],[43.646205,1.402638],[43.646279,1.402607],[43.64625,1.402622],[43.64623,1.402638],[43.646074,1.402739],[43.646024,1.402763],[43.645889,1.402837],[43.645843,1.402854],[43.645746,1.402871],[43.645621,1.402905],[43.6456,1.402912],[43.645552,1.40292],[43.645418,1.402962],[43.64539,1.402978],[43.64534,1.402991],[43.645221,1.403038],[43.64508,1.40308],[43.645038,1.4031],[43.644959,1.403128],[43.644852,1.403158],[43.644811,1.403177],[43.644685,1.40323],[43.644588,1.403266],[43.644453,1.403287],[43.644407,1.4033],[43.644314,1.40332],[43.644252,1.403335],[43.644226,1.403342],[43.644074,1.403374],[43.643963,1.403384],[43.643768,1.403388],[43.643677,1.403398],[43.643528,1.403435],[43.643455,1.40345],[43.643432,1.403457],[43.64331,1.40351],[43.643218,1.403534],[43.643074,1.403574],[43.643001,1.403598],[43.642861,1.403648],[43.642808,1.403661],[43.642756,1.403677],[43.642664,1.403679],[43.642586,1.403703],[43.642387,1.403773],[43.642347,1.403789],[43.642303,1.403802],[43.642215,1.403825],[43.64208,1.403853],[43.642039,1.403873],[43.641997,1.403889],[43.641907,1.403911],[43.641865,1.403926],[43.64179,1.403942],[43.641695,1.403969],[43.641556,1.404017],[43.641509,1.404025],[43.641427,1.404039],[43.64135,1.404052],[43.641267,1.40406],[43.641054,1.404107],[43.641013,1.404123],[43.640927,1.40415],[43.640757,1.404163],[43.640677,1.404175],[43.640636,1.404181],[43.640595,1.404194],[43.640513,1.404223],[43.64047,1.404236],[43.640386,1.404261],[43.640347,1.404269],[43.640244,1.404296],[43.640217,1.404307],[43.640218,1.404308],[43.640258,1.404292],[43.640331,1.404259],[43.640379,1.404227],[43.640428,1.404211],[43.640568,1.404167],[43.640731,1.404123],[43.640809,1.404108],[43.640788,1.404118],[43.640701,1.404143],[43.640538,1.404189],[43.640465,1.404211],[43.640353,1.404258],[43.640306,1.404277],[43.640176,1.404299],[43.640145,1.404306],[43.640025,1.404319],[43.639925,1.404342],[43.6399,1.404352],[43.639805,1.4044],[43.639776,1.404402],[43.639672,1.404423],[43.639597,1.404427],[43.639534,1.404441],[43.639473,1.404458],[43.639449,1.404467],[43.6393,1.40452],[43.639225,1.404527],[43.639141,1.404537],[43.638996,1.404555],[43.638874,1.404603],[43.638858,1.404605],[43.638743,1.404622],[43.6387,1.404637],[43.638621,1.404656],[43.638489,1.404684],[43.638354,1.404725],[43.638333,1.404729],[43.638295,1.404734],[43.638246,1.404736],[43.638129,1.404744],[43.638082,1.404752],[43.637958,1.404749],[43.637789,1.40475],[43.637741,1.404765],[43.637616,1.404797],[43.637467,1.404834],[43.637393,1.40485],[43.637263,1.404871],[43.637221,1.40487],[43.637083,1.404854],[43.637061,1.404856],[43.636929,1.404903],[43.636896,1.404911],[43.636761,1.404912],[43.636742,1.404915],[43.636599,1.404922],[43.636574,1.404916],[43.636518,1.404922],[43.636453,1.40494],[43.636412,1.40495],[43.636336,1.404954],[43.636219,1.404975],[43.636213,1.404992],[43.636208,1.405067],[43.636181,1.40515],[43.636137,1.40532],[43.636107,1.405424],[43.636079,1.405538],[43.636066,1.405596],[43.636049,1.405684],[43.636029,1.405862],[43.636027,1.40589],[43.636023,1.40592],[43.63598,1.406093],[43.635974,1.406154],[43.636002,1.406339],[43.63601,1.406367],[43.636052,1.406548],[43.63607,1.406639],[43.63611,1.406792],[43.636143,1.40694],[43.636166,1.406998],[43.636181,1.407058],[43.636217,1.407157],[43.6363,1.407303],[43.636329,1.407358],[43.636421,1.40751],[43.636505,1.407634],[43.636589,1.407757],[43.636675,1.407906],[43.636712,1.407981],[43.636726,1.40801],[43.636809,1.408153],[43.636836,1.4082],[43.63689,1.408288],[43.636949,1.408387],[43.63698,1.408436],[43.637013,1.408487],[43.637046,1.408538],[43.637078,1.40859],[43.637168,1.40874],[43.637197,1.408788],[43.637227,1.408836],[43.637288,1.408932],[43.637348,1.409028],[43.637467,1.409219],[43.637497,1.409264],[43.637644,1.409489],[43.637788,1.409713],[43.637852,1.409805],[43.637947,1.409931],[43.638011,1.410007],[43.63805,1.410037],[43.638175,1.410096],[43.638258,1.410107],[43.638339,1.410093],[43.638381,1.410081],[43.638529,1.410023],[43.638556,1.410008],[43.638482,1.410036],[43.638302,1.410079],[43.638257,1.410081],[43.638171,1.410073],[43.638089,1.410038],[43.638049,1.410014],[43.638013,1.409982],[43.63798,1.409942],[43.637924,1.409872],[43.637908,1.40986],[43.637917,1.409873],[43.638008,1.409965],[43.638169,1.410066],[43.638188,1.410072],[43.63823,1.410085],[43.638342,1.410081],[43.638472,1.410024],[43.638496,1.410015],[43.638518,1.410006],[43.638587,1.409996],[43.638652,1.409977],[43.638696,1.409971],[43.638714,1.409983],[43.638753,1.410045],[43.638807,1.410126],[43.638824,1.410148],[43.638855,1.410188],[43.638919,1.410262],[43.638972,1.410326],[43.639023,1.410387],[43.639123,1.410505],[43.639222,1.410615],[43.639271,1.410675],[43.639303,1.410718],[43.639383,1.41082],[43.639475,1.41094],[43.639582,1.41106],[43.639599,1.411078],[43.639698,1.411195],[43.639714,1.411213],[43.639818,1.411326],[43.639888,1.411399],[43.639989,1.411515],[43.640097,1.411626],[43.640153,1.411678],[43.640173,1.411698],[43.64028,1.411832],[43.640347,1.41189],[43.640423,1.411979],[43.640512,1.412086],[43.640618,1.412208],[43.640672,1.412267],[43.640772,1.412386],[43.640877,1.412504],[43.640912,1.412546],[43.641004,1.412669],[43.641023,1.41269],[43.641113,1.412822],[43.641165,1.41288],[43.641281,1.412998],[43.64133,1.413065],[43.641348,1.413088],[43.641465,1.413226],[43.641551,1.413334],[43.641669,1.41347],[43.641773,1.413623],[43.641826,1.41374],[43.641869,1.41391],[43.641925,1.414052],[43.641954,1.414111],[43.641971,1.414198],[43.641992,1.414286],[43.642094,1.414539],[43.642204,1.414784],[43.642254,1.414885],[43.642358,1.415099],[43.642456,1.415312],[43.642482,1.415363],[43.642506,1.415418],[43.64255,1.415522],[43.642591,1.415612],[43.642689,1.415829],[43.6427,1.415841],[43.642706,1.41584],[43.642692,1.415806],[43.642672,1.415769],[43.642551,1.415529],[43.642526,1.415468],[43.6425,1.415422],[43.642469,1.415382],[43.642475,1.415406],[43.64252,1.415489],[43.64255,1.415544],[43.64261,1.415667],[43.642666,1.415804],[43.64269,1.415914],[43.642717,1.416006],[43.642751,1.416026],[43.642785,1.416034],[43.642873,1.416098],[43.642892,1.41611],[43.642924,1.416124],[43.64297,1.416153],[43.643026,1.416202],[43.643088,1.416243],[43.643172,1.416307],[43.643195,1.41633],[43.643266,1.416422],[43.643315,1.416495],[43.643381,1.416619],[43.643417,1.416697],[43.643442,1.416755],[43.643478,1.416817],[43.643542,1.416944],[43.643614,1.417094],[43.643654,1.417182],[43.643731,1.417307],[43.643763,1.417362],[43.64386,1.417512],[43.643889,1.417567],[43.643976,1.417714],[43.644002,1.417777],[43.644073,1.41793],[43.644135,1.418033],[43.64419,1.418142],[43.644225,1.418219],[43.644251,1.418268],[43.644268,1.418292],[43.64434,1.418427],[43.644391,1.418526],[43.644521,1.418781],[43.644605,1.418915],[43.644754,1.419133],[43.644814,1.419218],[43.644869,1.4193],[43.644994,1.419471],[43.645152,1.419637],[43.645233,1.41973],[43.645377,1.419946],[43.645467,1.420074],[43.645557,1.420186],[43.645609,1.420253],[43.645704,1.420375],[43.645856,1.420569],[43.645939,1.420694],[43.645939,1.420689],[43.645926,1.420666],[43.645854,1.420574],[43.645718,1.420409],[43.645584,1.420252],[43.645526,1.420173],[43.645498,1.42014],[43.645471,1.420118],[43.645475,1.420127],[43.645564,1.420248],[43.645638,1.42039],[43.645703,1.420488],[43.645829,1.420617],[43.645887,1.420671],[43.645924,1.420723],[43.645965,1.420881],[43.645955,1.420908],[43.645939,1.420927],[43.645884,1.420961],[43.645864,1.420975],[43.645741,1.421063],[43.64571,1.421096],[43.645617,1.421227],[43.645605,1.421263],[43.645601,1.421289],[43.645597,1.421364],[43.64559,1.421379],[43.645584,1.421485],[43.645587,1.421509],[43.645587,1.421509],[43.645587,1.421509],[43.645542,1.421925],[43.64547,1.421911],[43.645333,1.421885],[43.645294,1.421896],[43.645206,1.4219],[43.645158,1.421906],[43.645051,1.421904],[43.645017,1.421899],[43.644977,1.421894],[43.644898,1.421903],[43.644837,1.421905],[43.64475,1.421904],[43.644681,1.421906],[43.644602,1.421899],[43.644561,1.421894],[43.644477,1.421893],[43.6444,1.421901],[43.644309,1.421906],[43.644118,1.421928],[43.644073,1.421938],[43.643998,1.421961],[43.64384,1.422001],[43.643623,1.422051],[43.64342,1.422094],[43.643262,1.422123],[43.643076,1.422145],[43.643039,1.422157],[43.64287,1.422254],[43.642799,1.422304],[43.64264,1.422376],[43.642719,1.422331],[43.642882,1.42221],[43.64292,1.422179],[43.643099,1.422077],[43.643103,1.422074],[43.643085,1.422075],[43.643074,1.422083],[43.642992,1.422145],[43.6429,1.422203],[43.642819,1.422265],[43.64274,1.42232],[43.642606,1.422377],[43.642441,1.422373],[43.642376,1.422362],[43.642352,1.42236],[43.642256,1.422348],[43.642167,1.42233],[43.642036,1.422293],[43.641949,1.42229],[43.641814,1.422258],[43.641791,1.422253],[43.64164,1.422237],[43.64162,1.422227],[43.641576,1.422226],[43.641477,1.422221],[43.641432,1.422209],[43.641342,1.422193],[43.641177,1.422179],[43.64104,1.422166],[43.641017,1.422161],[43.640879,1.422141],[43.640826,1.422147],[43.640678,1.422127],[43.640616,1.42212],[43.640485,1.422094],[43.640442,1.422092],[43.6403,1.422077],[43.640209,1.422048],[43.640072,1.422035],[43.639997,1.422027],[43.639859,1.422014],[43.639835,1.422008],[43.639702,1.42199],[43.639642,1.421969],[43.639502,1.421938],[43.639387,1.421926],[43.639243,1.421898],[43.63915,1.421894],[43.639085,1.421898],[43.638938,1.421879],[43.638913,1.421873],[43.638779,1.421847],[43.63876,1.421837],[43.638656,1.421824],[43.63858,1.421811],[43.638461,1.421803],[43.638238,1.421786],[43.638209,1.421786],[43.638134,1.421778],[43.638093,1.421769],[43.638053,1.421764],[43.638012,1.421755],[43.637817,1.421708],[43.63778,1.421702],[43.6376,1.42168],[43.637482,1.421672],[43.637327,1.421661],[43.637118,1.421632],[43.636916,1.421593],[43.636842,1.421587],[43.636757,1.421577],[43.636537,1.421525],[43.636501,1.421522],[43.636474,1.421506],[43.636615,1.421485],[43.636827,1.421502],[43.636904,1.421516],[43.636933,1.421523],[43.636949,1.421522],[43.636937,1.421517],[43.636839,1.421488],[43.636706,1.421499],[43.636633,1.421489],[43.636562,1.421491],[43.636454,1.421477],[43.636303,1.421467],[43.636255,1.421465],[43.636232,1.421456],[43.636191,1.421449],[43.636081,1.421429],[43.636039,1.421422],[43.635925,1.421397],[43.635857,1.421389],[43.635723,1.421365],[43.6357,1.421367],[43.635554,1.421361],[43.635504,1.42135],[43.635378,1.421343],[43.635316,1.421338],[43.635296,1.421332],[43.635168,1.421284],[43.635129,1.421276],[43.635109,1.421267],[43.634978,1.421237],[43.63489,1.42125],[43.634874,1.421305],[43.634865,1.42143],[43.634847,1.421593],[43.634861,1.421669],[43.634896,1.421693],[43.635047,1.421732],[43.63515,1.421756],[43.635204,1.421758],[43.635231,1.421761],[43.635359,1.421757],[43.635369,1.421739],[43.635367,1.42172],[43.635354,1.421706],[43.635235,1.4217],[43.63521,1.421706],[43.635197,1.421704],[43.635199,1.421695],[43.635196,1.421687],[43.635192,1.421686],[43.635139,1.42167],[43.635088,1.421661],[43.635061,1.421654],[43.634929,1.421623],[43.634819,1.421594],[43.6348,1.421592],[43.63474,1.421588],[43.634663,1.421595],[43.634532,1.421599],[43.634453,1.421596],[43.634334,1.421673],[43.634316,1.421688],[43.634274,1.421718],[43.634236,1.42174],[43.634185,1.421768],[43.634069,1.421859],[43.633993,1.421927],[43.633975,1.421939],[43.633929,1.421956],[43.633851,1.42198],[43.633826,1.421986],[43.633703,1.42204],[43.633635,1.422068],[43.633512,1.422126],[43.633383,1.422171],[43.63334,1.422185],[43.633188,1.422233],[43.633109,1.422251],[43.63307,1.42226],[43.632972,1.422309],[43.632857,1.422366],[43.632734,1.422413],[43.632542,1.422517],[43.632507,1.422534],[43.632403,1.422587],[43.63224,1.42268],[43.6322,1.422701],[43.632167,1.422718],[43.631996,1.422803],[43.631847,1.422886],[43.631643,1.422991],[43.631525,1.423038],[43.631344,1.423088],[43.631273,1.423125],[43.631089,1.423227],[43.631061,1.42324],[43.6309,1.423324],[43.630707,1.423428],[43.630654,1.423465],[43.630645,1.423475],[43.630666,1.423473],[43.630765,1.423424],[43.630805,1.423402],[43.630991,1.423276],[43.631016,1.423256],[43.631191,1.423149],[43.631256,1.423105],[43.631337,1.423061],[43.631346,1.423064],[43.631325,1.423088],[43.631307,1.423099],[43.631284,1.423109],[43.631164,1.423172],[43.63103,1.423245],[43.630963,1.423282],[43.630904,1.42331],[43.630765,1.423383],[43.63068,1.423456],[43.63067,1.423486],[43.630643,1.423585],[43.630602,1.423658],[43.630579,1.423771],[43.630601,1.423896],[43.630631,1.424033],[43.630675,1.424202],[43.630699,1.424295],[43.630749,1.424483],[43.630781,1.424595],[43.630807,1.424729],[43.630824,1.424803],[43.630847,1.42499],[43.630859,1.425046],[43.630906,1.425236],[43.630919,1.425363],[43.630925,1.425427],[43.630961,1.425513],[43.630972,1.425572],[43.630984,1.425653],[43.631015,1.425802],[43.631026,1.425854],[43.631035,1.425896],[43.631048,1.425946],[43.631101,1.426185],[43.631119,1.42628],[43.631145,1.426377],[43.631193,1.426562],[43.631216,1.42666],[43.63128,1.426917],[43.631309,1.427017],[43.631356,1.427217],[43.631416,1.427418],[43.631469,1.427622],[43.631503,1.427762],[43.631509,1.427801],[43.631501,1.427823],[43.631493,1.427806],[43.631453,1.427632],[43.631393,1.427405],[43.631362,1.427315],[43.631368,1.42734],[43.631407,1.427473],[43.631481,1.427654],[43.631499,1.42774],[43.631536,1.427867],[43.631547,1.427892],[43.631567,1.427981],[43.631594,1.428098],[43.631608,1.428184],[43.631618,1.428262],[43.631628,1.428341],[43.631668,1.428525],[43.631683,1.428658],[43.631726,1.428856],[43.631733,1.428886],[43.631759,1.429078],[43.631763,1.429136],[43.631792,1.429315],[43.631812,1.429365],[43.631823,1.429419],[43.631838,1.429543],[43.631859,1.429733],[43.631883,1.429841],[43.631895,1.429943],[43.631899,1.430043],[43.631907,1.430096],[43.631923,1.430201],[43.631943,1.430306],[43.631973,1.430518],[43.631992,1.430675],[43.632037,1.430867],[43.6321,1.431108],[43.632127,1.431197],[43.632138,1.431247],[43.632145,1.431284],[43.632162,1.431412],[43.6322,1.431631],[43.632209,1.431679],[43.632203,1.43165],[43.632186,1.431555],[43.632174,1.431499],[43.632137,1.431325],[43.632115,1.431229],[43.632115,1.431251],[43.632116,1.431282],[43.632137,1.431397],[43.632186,1.431637],[43.632213,1.431766],[43.632353,1.43186],[43.632376,1.431866],[43.632495,1.431826],[43.632579,1.43178],[43.632639,1.431746],[43.632731,1.431705],[43.632768,1.431686],[43.632854,1.431685],[43.632878,1.431713],[43.632911,1.431825],[43.632949,1.431916],[43.632963,1.431952],[43.632969,1.431993],[43.633004,1.43211],[43.633065,1.432307],[43.633081,1.43236],[43.633125,1.432522],[43.633162,1.432626],[43.633214,1.432826],[43.633236,1.432922],[43.633319,1.433187],[43.633339,1.433302],[43.633331,1.433288],[43.633286,1.433147],[43.633271,1.433068],[43.633332,1.433242],[43.633354,1.433358],[43.633352,1.433495],[43.63339,1.433643],[43.633396,1.433814],[43.633399,1.434004],[43.633417,1.434107],[43.633423,1.434203],[43.63342,1.434294],[43.633415,1.434421],[43.633413,1.434676],[43.633444,1.434899],[43.633448,1.435016],[43.633435,1.435301],[43.633425,1.435395],[43.63342,1.435442],[43.633396,1.435487],[43.633375,1.435531],[43.633263,1.435742],[43.633176,1.435809],[43.633138,1.435812],[43.632987,1.435711],[43.632886,1.435604],[43.632745,1.435479],[43.632577,1.435373],[43.632515,1.435366],[43.63235,1.435453],[43.632264,1.435556],[43.632164,1.435663],[43.632138,1.435822],[43.632177,1.435954],[43.632222,1.436023],[43.632342,1.436227],[43.632393,1.436288],[43.63253,1.436451],[43.632586,1.436513],[43.632723,1.436676],[43.632759,1.436759],[43.632929,1.436932],[43.63308,1.437113],[43.633105,1.437148],[43.633184,1.437263],[43.633261,1.437317]],"velocity_smooth":[0,1.3,1.5,1.8,1.7,2.1,2.2,2.2,3,3.2,3.2,3.1,2.9,2.7,2.6,2.5,2,2,2.3,2.6,2.5,2.7,3.1,3.2,3.5,3.4,3.1,2.8,2.8,2.8,2.9,2.9,2.8,2.8,2.8,2.7,2.7,2.7,2.6,2.6,2.6,2.5,2.5,2.6,2.8,2.7,2.7,2.5,2.5,2.6,2.6,2.5,2.5,2.6,2.5,2.3,2.3,2.5,2.6,2.6,2.6,2.6,2.7,2.8,2.8,2.9,3,2.9,2.7,2.6,2.8,2.7,2.8,2.4,2.6,2.8,1.5,1.3,2.6,2.8,2.7,2.9,2.9,2.9,2.9,2.9,2.9,2.8,2.8,3,3.1,3,3,3.1,3.1,3,3,3,2.9,2.9,2.9,2.9,2.9,2.8,2.8,3,2.8,2.6,2.5,2.6,2.6,2.6,0.4,0.1,2.2,2.6,2.8,2.7,2.7,2.5,2.5,2.6,2.7,2.7,2.8,2.9,2.9,2.8,2.9,3,3,2.6,2.6,2.8,0.7,0.1,2.4,3.2,3.4,3.2,3.2,3.2,3.3,3.2,3.2,3.1,3.2,3.3,3.2,3,2.9,2.9,2.9,3,3,3,2.9,3,3,3,2.9,2.8,2.9,3,3,2.8,2.8,2.8,2.8,2.8,2.8,2.6,2.5,2.6,2.7,2.8,2.8,2.8,2.7,2.6,2.6,2.7,2.7,2.6,2.7,2.7,2.6,2.6,2.7,2.7,2.7,2.7,2.6,2.7,2.9,2.7,2.5,2.6,2.4,2.2,1.8,2.2,2.8,2.7,2.4,2.2,2.1,2.3,2.5,2.8,2.9,2.9,4,4.7,5.3,5,4.9,4.9,5,5,5,5,4.9,4.7,4.6,4.6,4.6,4.6,4.5,4.3,4.3,4.6,4.6,4.4,4.3,4.1,2.8,2.6,2.2,4.7,5,4.8,4.8,4.8,4.9,4.8,4.4,2.9,2.4,2.9,3,2.9,2.7,2.6,2.8,2.8,2.7,2.7,2.7,2.5,2.4,2.7,2.8,2.8,2.6,2.6,2.6,2.6,2.8,2.8,2.8,2.9,2.9,3.1,3,2.5,2.8,2.9,2.8,2.9,2.9,2.6,2.4,2.3,2.4,2.6,2.8,2.6,2.5,2.7,2.8,2.7,2.5,2.5,2.6,2.6,2.2,2.2,2.4,2.4,2.5,2.6,2.5,2.4,2.5,3.6,4,4.7,5,4.9,4.8,4.7,4.9,5,5,5,4.7,4.6,4.6,4.6,4.3,4.4,4.2,4.3,4.3,4.3,4.4,4.8,5,5.4,5.4,4.6,3.7,3.2,4.8,5.4,5.4,5.4,3.9,3.3,1.8,2.3,2.5,2.5,2.4,2.6,2.9,2.9,2.5,2.5,2.6,2.4,2.5,2.8,2.9,2.7,2.8,2.9,2.5,2.4,2.4,2.8,2.8,2.8,2.5,2.7,2.8,2.8,2.6,2.6,2.5,2.4,2.5,2.4,2.4,2.2,3,3.3,3.1,2.6,2.5,1.6,1.7,2.8,3.1,4.2,5,4.8,4.9,3.7,3.7,3.7,3.3,3,2.2,1.9,2.3,2.6,2.6,2.8,2.6,2.5,2.5,2.5,2.5,2.7,2.6,2.6,2.6,2.3,2.4,2.5,2.7,2.9,3,2.7,2.4,2.4,2.4,3.3,3.9,4.8,4.8,5,4.9,5,4.7,4.9,5,4.7,4.7,4.7,4.8,5.1,5.1,5,4.9,4.6,4.6,4.4,4.9,5,4.8,4.7,5.1,4.9,4.6,4.8,4.8,4.9,4.9,5.1,5.1,4.9,4.7,4.7,4.8,4.7,4.7,4.4,2.8,2.3,2.5,3.5,3.7,4.5,5,4.9,4.7,4.7,4.5,4.4,2.4,2,2.6,2.8,2.7,2.6,2.6,2.6,2.7,2.6,2.5,2.5,2.6,2.8,2.8,2.6,2.5,2.6,2.7,2.6,2.6,2.6,2.7,2.7,2.7,2.7,2.6,2.5,2.5,2.5,2.6,2.6,2.5,2.6,2.6,2.7,2.8,2.6,2.5,2.6,2.6,2.5,2.9,3,2.7,2.5,2.6,2.5,2.6,2.5,2.4,2.5,2.5,2.7,2.7,2.6,2.7,2.2,1.8,1.7,1.6,0.9,1.1,1.8,1.8,1.7,1.6,2.2,2.5,2.7,2.7,2.8,2.8,3,3,2.9,2.9,3,2.9,2.9,2.9,2.8,2.8,2.7,2.7,2.8,2.7,2.7,2.7,2.7,2.8,2.8,2.7,2.7,2.7,2.8,2.8,2.7,2.6,2.3,1.8,1.9,2.8,2.8,3.1,3.7,5.4,5.5,5.4,5.2,5.3,5.4,5.5,5.2,4.6,3.7,3.7,4.7,4.6,3.5,2.2,2.6,2.7,2.6,2.6,2.6,2.6,2.7,2.7,2.7,2.6,2.7,2.9,2.9,2.9,2.8,2.7,2.3,2.2,1.4,1.1,1.7,2.5,2.8,2.7,2.7,2.9,3.3,4.3,4.5,4.5,4.5,4.6,4.8,5,4.7,4.7,4.6,4.6,4.8,4.7,4.7,4.8,4.8,2.8,2,3.2,4.8,4.7,4.1,3.4,1.6,1.9,2.1,2.1,2.2,2.3,2.2,2.2,2.6,2.6,2.7,2.5,2.6,2.6,2.7,2.7,2.6,2.5,2.6,2.9,2.9,2.8,2.7,2.5,2.4,2.5,2.6,2.7,2.8,2.7,2.6,2.5,2.3,2.3,2.8,3.3,3.8,3.9,4.5,4.8,5.2,4.7,4.7,4.7,4.7,4.7,4.8,4.5,4.6,4.6,4.4,4.2,5.1,5.3,4.9,4.5,4.3,4.3,3.8,2.7,2.5,4.2,4.9,2.9,2,2.1,3.1,3.1,2.8,2.7,2.3,2.3,2.4,2.5,2.6,2.7,2.7,2.8,2.7,2.6,2.8,3,2.8,2.4,2.6,2.6,2.5,2.6,2.5,2.5,2.9,3,3.4,3.5,3,2.8,2.8,2.4,2.5,2.7,2.7,2.7,2.8,2.8,3.2,3.8,4.5,4.6,4.6,4.7,5,5,5,5,4.9,4.7,4.8,5.3,5.3,5.1,4.6,4.5,4.7,4.8,4.8,4.8,4.7,4.6,4.6,4.6,4.7,4.8,4.7,4.3,2.9,2.5,1.6,2.7,3.8,4.1,5.5,4.9,3.9,2.3,2.5,3.2,3,3,3.1,2.5,2.3,2.4,2.7,2.8,2.8,2.9,2.5,2.2,2.2,2.3,2.4,2.8,2.8,2.5,2.5,2.5,2.3,2.4,2.5,2.8,2.6,2.5,2.5,2.4,2.4,2.6,2.6,2.4,2.7,3,2.8,2.8,2.8,2.5,2.4,2.5,2.5,2.5,2.4,2.3,2.4,2.6,2.7,2.5,2.3,2.4,2.6,2.4,2.1,2.1,2.2,2.4,2.4,2.3,2.4,2.5,2.4,2.4,2.4,2.5,2.5,2.5,2.5,2.5,2.5,2.6,2.6,2.5,2.6,2.4,2.4,2.6,2.7,2.7,2.7,2.6,2.5,2.5,3.5,3.9,4.1,4.9,5,5,5.3,5.4,5.4,5.3,5.2,5.2,5.1,5.1,5.1,4.9,4.9,4.9,5,4.8,4.8,4.8,4.8,4.7,4.6,4.4,3.4,2.4,4.1,5.1,5,4.8,4.8,4.8,4.8,4.6,3.1,2.5,2.8,3.2,3.1,3,2.5,2.5,2.6,2.6,2.6,2.5,2.5,2.4,2.3,2.2,2.3,2.3,2.3,2.4,2.6,2.5,2.6,2.7,2.4,2.4,2.4,2.4,2.5,2.4,2.4,2.4,2.5,2.4,2.5,2.5,2.5,2.7,2.8,2.8,2.7,2.6,2.6,2.5,2.5,2.5,2.4,2.4,2.5,2.5,2.6,2.6,2.6,2.8,2.7,2.7,2.8,2.8,2.9,2.5,2.4,2.6,3.4,4.4,4.7,4.7,5.1,5.1,5.1,5.1,5,4.7,4.2,3.7,3.3,2.9,1.8,5.5,5.8,5.6,4.8,2.3,2.1,2.8,2.9,3.1,3.1,2.9,2.4,2.3,2.5,2.7,2.9,2.8,2.6,2.5,2.6,2.8,2.8,2.7,2.5,2.5,2.6,2.8,3.2,2.7,2.6,2.7,2.7,2.7,2.7,2.6,2.7,2.6,2.5,2.7,2.6,2.4,2.5,3.5,4.7,5,4.9,4.8,4.8,4.7,4.8,4.6,4.2,4.4,4.8,4.7,4.3,4.4,4.7,4.1,2.8,2.7,2.7,4.4,5,4.8,4.7,3.3,2.9,2.4,2.8,2.8,2.8,2.8,2.7,2.8,2.7,2.7,2.3,2.3,2.5,2.5,2.4,2.6,2.5,2.3,1.9,1.8,2,2.6,2.6,2.6,2.6,2.4,2.3,2,2.2,2.1,2,2,2.2,2.2,2.7,3.5,3.7,4.2,4.5,4.5,4.7,4.5,4.4,4.4,4.4,4.7,4.7,4.5,4.3,4.2,4.1,4.2,3.5,3.1,4.3,5.1,3.8,3.1,2.6,2.5,2,2.7,3.6,3.4,3.6,3.4,2.8,2.8,2.7,3,2.8,2.5,2.5,2.5,2.8,2.7,2.7,2.6,2.7,2.5,2.9,2.8,2.6,2.6,2.7,2.8,2.6,2.4,2.4,2.6,2.6,2.6,2.6,2.6,2.6,2.5,2.4,2.5,2.6,2.6,2.6,2.5,2.6,2.8,2.6,2.5,2.8,3.4,4.4,4.8,4.7,4.5,4.5,4.1,4.4,4.4,4.3,4,4.2,4.3,4.5,4.6,4.4,4.5,4.3,4.1,3.4,3,4.4,4.6,4.5,2.8,2.5,2.1,2.6,2.8,2.7,2.9,2.9,2.8,2.7,2.5,2.4,2.4,2.5,2.5,2.5,2.5,2.7,2.7,2.8,2.6,2.6,2.4,2.4,2.4,2.4,2.3,2.2,2.5,2.6,2.5,2.2,2.7,2.9,2.9,2.9,2.9,2.7,2.5,2.5,2.6,2.7,2.2,2,0.1,0,1.3,1.7,3,3,2.8,2.4,2.4,2.5,2.6,2.3,2.3,2.4,2.4,2.4,2.1,2.3,2.5,2.5,2.5,2.8,2.8,3.4,3.7,4.5,4.9,4.9,4.4,4.4,4.4,4.1,4.2,4.6,4.6,4.5,4.4,4,4.1,4,4,4.2,4.2,4.2,4.3,4.1,4.3,4.2,3.7,3.8,3.7,3.4,2,2.8,3.2,4.7,4.4,4.1,4.2,3.5,2.2,2,1.3,1.5,2.8,2.7,2.7,3,2.9,2.8,2.8,2.8,2.7,2.5,2.5,2.4,2.4,2.5,2.7,2.6,2.3,2.2,2.4,2.5,2.6,2.6,2.5,2.6,2.6,2.8,3.8,3.9,4.1,4.1,4.1,4,4,4,4,4.3,4.4,4.3,4.3,4.4,4.2,4.1,3,2.8,3.2,4.9,3.9,2,2.3,2.8,2.6,2.3,2.3,2.3,2.5,2.4,2.3,2.1,2.4,2.6,2.8,2.8,2.6,2.6,2.4,2.4,2.4,2.5,2.6,2.5,2.5,3.3,3.5,4.2,4.4,4.4,4.3,4.2,4.1,4.1,4.1,4,3.5,3.6,2.8,2.8,2.5,2.8,4.6,3.8,2,2.1,2.3,3.3,3.1,2.8,2.9,2.7,2.6,2.5,2.6,2.5,2.4,2.7,2.6,2.6,2.7,3,3.3,3.9,4.4,4.5,4.7,4.4,4.2,4.5,3.7,2.2,3,3,2.7,3.2,3,2.6,2.4,2.4,2.7,2.7,2.5,3,3.9,4.3,4.6,4.6,4.4,4.3,4.3,4,4.2,4,4.1,4.6,4.7,4.1,3.9,3.9,3.8,4,3.8,3.5,3.6,3.8,4.1,4.1,3.9,4,4,4,3.9,4.2,4.4,4.3,3.7],"heartrate":[58,56,57,63,64,68,71,73,76,77,77,80,83,83,85,89,89,91,93,96,97,99,102,105,106,108,112,115,116,118,120,125,124,126,130,131,134,133,132,135,136,133,135,137,138,139,142,142,142,139,137,138,138,136,138,140,140,142,144,144,145,145,147,144,144,144,144,143,142,142,142,142,142,141,143,144,143,141,140,140,139,136,137,137,135,136,139,140,137,134,132,132,131,127,127,128,125,125,122,121,119,119,119,121,121,121,124,126,127,127,130,128,118,119,119,120,118,120,119,123,123,123,123,124,128,127,127,128,131,131,133,132,132,133,122,122,122,125,124,126,129,130,130,131,129,130,132,129,129,130,127,127,124,126,127,128,130,129,128,131,130,132,134,133,134,132,130,130,132,132,132,132,135,136,137,136,137,138,138,134,135,133,133,136,137,134,135,134,132,129,129,129,131,130,131,132,135,136,135,136,136,136,134,133,133,133,134,132,132,134,134,135,136,138,139,140,140,141,143,142,142,145,144,143,146,146,149,150,147,150,150,153,152,151,152,156,153,153,156,157,157,160,161,158,161,161,161,161,160,159,156,155,152,149,149,147,143,145,142,142,139,136,135,132,133,133,130,126,124,126,125,122,122,121,121,118,117,119,118,120,122,119,119,118,116,115,118,118,117,117,116,117,118,115,117,115,115,114,115,116,119,122,123,123,124,127,127,130,135,138,141,145,148,147,150,150,153,153,153,154,155,155,155,158,156,159,159,159,159,159,162,163,160,162,162,163,164,164,163,163,163,161,158,156,153,152,151,150,148,145,144,140,137,134,133,129,128,128,125,126,126,123,120,119,116,117,120,120,122,122,120,120,121,121,120,120,120,119,119,117,116,115,115,114,115,117,114,116,117,114,116,116,116,116,116,119,118,117,116,118,118,116,116,117,117,116,116,116,114,114,116,114,115,114,115,112,111,112,115,118,124,128,130,133,137,139,142,143,144,146,149,150,150,149,152,154,153,155,156,155,155,158,157,158,158,159,162,161,161,160,164,161,163,164,165,166,167,166,165,167,165,167,164,167,164,167,167,168,168,166,166,166,166,164,162,163,160,159,156,152,148,144,144,142,139,138,135,132,129,126,128,124,125,125,125,122,120,121,118,119,118,117,118,120,120,118,118,120,117,117,114,115,113,114,114,114,114,115,116,116,114,114,115,116,115,117,116,116,119,118,117,117,115,114,114,112,112,109,108,109,110,110,113,112,112,110,111,111,112,111,111,112,113,114,114,114,116,116,119,117,119,119,119,119,120,120,120,123,121,118,120,122,121,121,120,118,121,123,124,128,129,128,130,131,134,136,138,140,141,142,143,144,145,149,157,154,150,150,149,149,149,148,145,142,142,139,137,137,134,130,127,127,127,125,128,128,125,125,126,126,129,135,137,140,143,145,150,153,155,158,158,161,162,163,161,162,163,163,163,163,166,164,164,162,162,159,157,155,154,151,151,152,150,147,142,140,141,137,135,133,133,132,130,130,127,126,124,123,122,122,122,122,119,119,118,119,118,121,122,125,128,129,126,131,135,139,144,144,148,151,153,153,155,155,155,157,156,156,157,156,158,159,160,162,162,163,163,165,163,162,161,160,159,157,156,156,152,150,149,146,142,140,139,136,133,132,129,130,129,129,126,123,122,121,121,118,119,118,121,119,117,119,121,122,122,120,121,118,118,123,128,128,130,135,142,146,149,149,152,152,155,156,157,156,157,159,159,159,160,160,157,157,163,163,165,164,166,168,166,164,163,166,164,165,167,165,166,165,165,163,160,160,158,157,152,153,150,146,146,143,142,139,135,135,134,134,131,131,130,129,129,129,126,124,125,125,123,120,121,121,119,119,119,117,118,116,117,119,120,120,117,117,117,118,118,118,119,119,118,115,114,114,115,118,120,122,119,120,118,117,120,120,120,122,123,123,122,122,119,117,120,117,118,118,119,119,121,118,118,121,122,125,126,129,134,138,137,131,132,135,139,142,152,155,158,155,157,156,159,159,160,163,163,164,165,164,165,166,168,167,167,168,165,167,167,166,166,167,168,167,165,165,168,167,165,161,160,157,154,152,153,150,148,147,144,141,140,137,139,134,130,132,130,129,126,123,125,125,125,124,124,123,122,122,121,119,122,125,124,125,123,121,122,123,123,124,124,127,121,120,121,122,123,121,118,118,118,118,121,123,125,127,128,130,134,134,134,134,137,135,135,136,141,143,141,140,139,139,140,143,142,145,144,146,148,146,148,153,158,157,157,154,150,147,148,145,145,142,140,137,135,132,132,129,128,125,125,124,124,124,124,124,121,123,123,124,127,129,131,133,134,134,134,135,136,136,139,138,141,141,143,143,142,141,141,144,146,147,145,144,144,145,146,149,150,148,151,151,152,153,153,151,148,145,145,146,141,136,133,133,130,131,131,128,128,128,131,128,126,125,125,125,127,130,130,130,134,137,137,140,143,146,147,150,152,155,156,157,158,159,159,160,161,162,162,162,162,161,161,161,163,164,161,161,158,157,154,153,150,146,145,143,140,139,139,136,137,136,133,133,130,128,127,127,127,126,126,124,123,126,127,125,125,123,121,121,123,125,125,123,120,120,120,121,123,122,122,124,128,129,128,132,140,143,146,146,148,148,148,147,150,153,159,158,161,159,159,158,159,159,161,161,161,161,161,157,157,154,154,153,149,149,145,142,141,138,139,139,136,134,134,131,132,129,127,127,127,127,129,130,133,135,134,133,132,131,127,127,126,126,125,125,121,121,117,115,115,116,118,115,114,114,113,114,113,114,114,114,114,114,117,120,121,124,123,122,125,125,126,129,128,133,134,137,140,143,143,146,147,150,153,153,150,152,156,156,157,157,159,158,160,161,161,161,160,163,160,162,160,161,160,162,162,162,162,162,162,162,161,160,157,155,154,151,148,147,144,142,143,142,139,136,134,132,130,133,125,123,122,122,121,124,125,125,122,122,126,132,135,137,137,138,142,146,146,148,150,154,155,158,159,159,159,158,158,158,159,158,157,154,152,149,148,145,144,143,139,136,137,138,138,137,138,137,134,132,131,131,132,132,135,136,136,139,136,145,149,148,147,148,153,152,153,155,154,155,155,155,155,157,157,158,158,157,156,154,152,151,148,148,145,145,144,143,140,138,139,140,141,142,145,148,149,152,153,153,154,153,154,156,156,157,154,155,154,152,149,148,147,146,148,148,151,153,150,154,152,154,155,157,156,158,161,161,161,161,160,160,159,160,159,159,160,159,159,157,158,159,159,160,158,161,161],"distance":[0.6,7.2,9.5,14.6,16.2,22.1,27.2,29.3,42.2,45.5,48.7,54.2,63.2,65.1,79.1,87.6,89.1,101.6,110,114.7,116.7,126.2,135.2,145.4,159.5,179,187.1,195.7,198.5,206.9,224.3,232.8,246.8,258.3,272,285.4,301.8,307.2,320.2,330.5,335.7,340.5,342.9,351.5,367.9,376.1,386.6,393.8,399,409.4,417.3,432.3,437.7,453.5,467.6,474.4,484,499.3,502,504.7,520.5,523,536.9,553.8,556.8,560,568.7,574.7,590.2,593,609.5,617.5,623.6,631.9,649.1,660.2,660.7,672,687,703.2,706.2,723.2,726.4,735.3,752.5,761.5,775.5,778.4,784,796.4,799.5,817.6,820.7,830.4,848.5,851.3,863.3,875.1,886.7,901.2,918.8,921.7,927.4,944.2,947,965,980.9,995.7,998.3,1014.1,1016.6,1021.6,1022,1022.9,1032.8,1038.5,1052.4,1068.4,1071,1086,1101.3,1104.2,1112.6,1123.4,1129.6,1147,1149.8,1160.9,1172.9,1175.7,1193.8,1196.8,1202,1216.6,1216.6,1217.6,1228.7,1249.4,1252.5,1268.4,1287.5,1294.2,1313.7,1316.8,1329.8,1341.8,1361.3,1367.8,1373.8,1391.6,1400.3,1403,1412.1,1429.9,1439.4,1457,1462.7,1481.1,1487.1,1499,1515.7,1532.7,1544.3,1562.7,1571,1587.8,1593.2,1604.7,1612.7,1629.6,1632.1,1647.6,1652,1668,1673.7,1690.3,1698.9,1715.1,1720.5,1728.1,1741.6,1757.4,1762.8,1772.8,1789.4,1792,1807.4,1810,1826.3,1837.1,1853.1,1855.9,1871.5,1874.7,1892,1899.2,1909.6,1919.7,1924,1927,1928.9,1937.3,1951,1961.3,1963.1,1966.2,1968,1977.6,1980.4,1997.2,2000.6,2004,2024.6,2045.9,2061.4,2085.7,2105.3,2124.8,2135.1,2140.1,2155,2159.9,2169.5,2192.9,2206.6,2230.1,2238.9,2262.1,2279.2,2283.5,2292.4,2315.5,2333.9,2354.8,2363.8,2379.3,2380.6,2384.6,2392.7,2412.9,2427.6,2437,2441.9,2446.7,2451.9,2456.6,2463.9,2466.3,2468.8,2486.4,2502.1,2512.9,2518,2534,2540.2,2545.7,2561.5,2564.3,2569.6,2576.9,2581.6,2592.8,2601.4,2604.3,2619.9,2622.4,2627.7,2632.9,2639.1,2655.6,2661.4,2673,2681.8,2701,2708.9,2716,2728.2,2745.1,2756.2,2773.8,2782.3,2792.2,2794.1,2798.5,2813.1,2830.1,2841.1,2855.8,2863.5,2879.7,2891.9,2906.9,2917.2,2929.1,2940.6,2950,2951.8,2953.9,2968.4,2971,2978.6,2991.4,2993.6,2995.3,3001,3013.4,3019.2,3029.2,3044.3,3053.6,3062.9,3086.5,3101.9,3107.8,3116.7,3121.4,3140.1,3148.8,3153.9,3158.4,3166.2,3170.7,3174.9,3192.4,3205.1,3209.4,3222.9,3233.6,3257.8,3282.1,3301,3309.5,3311.9,3328.6,3349.9,3355.6,3366.5,3382.4,3389.7,3389.7,3393.3,3408,3423.1,3433.1,3439.8,3451.4,3469,3474.4,3481.5,3492,3494.5,3506.5,3519.5,3531.5,3542.7,3555.5,3562.6,3566,3577.4,3585.3,3587.7,3599.4,3604.7,3607.1,3614.3,3631.6,3634.2,3637.1,3652.4,3660.3,3675.2,3677.2,3682.4,3687.1,3689.2,3695.8,3707.1,3712.3,3717.5,3722.8,3724.6,3732.3,3734.6,3749.3,3753,3770.5,3783,3786.8,3795.1,3805.2,3813.4,3827.2,3843.4,3859.8,3865.3,3876.6,3879.3,3894.9,3900.5,3917,3921.7,3937.1,3951.6,3966.7,3969.3,3985.6,3990.5,4006.3,4011.2,4022.4,4037.2,4042.1,4053.1,4059.7,4074.4,4086.8,4093.9,4096,4101,4110.6,4119.6,4129.6,4139.4,4144.4,4154,4159.4,4167.7,4173.8,4178.9,4187.3,4197.1,4202.4,4207.7,4212.6,4217.9,4232.7,4237.3,4245.6,4249.9,4254.6,4270.2,4275,4298.7,4303.4,4324.1,4342.3,4361.3,4366.2,4371.3,4376.5,4381.5,4386.7,4391.7,4401,4424.8,4438.8,4463.2,4467,4471.6,4478.8,4480.9,4485.6,4493.6,4498.3,4503.1,4508.2,4523.5,4547.5,4561,4565.8,4570.1,4573.9,4577.6,4590,4606.5,4612.7,4625.5,4638.7,4646.5,4662.3,4673.2,4683.4,4685.9,4700.8,4711.6,4717.4,4722.8,4738.2,4743.2,4756.6,4762.3,4772.3,4780.2,4795.9,4804.1,4812.2,4825.7,4839.3,4843.9,4848.4,4863.7,4871.3,4887.2,4894.5,4910,4917.6,4933.4,4938.9,4949.9,4959.6,4975.3,4977.7,4985.4,4990,5005.6,5020.4,5024.4,5040.1,5047.7,5062.8,5070.8,5084.9,5092.5,5107.6,5110.2,5126.4,5139.5,5155.5,5161.4,5172.9,5173.7,5174.8,5175.8,5177.6,5179,5188.3,5189.8,5194.5,5196.5,5205.7,5221.6,5229.8,5238,5243.6,5257.9,5270.2,5272.9,5280.9,5299,5304.6,5307.4,5322,5338.9,5341.6,5358.2,5363.5,5380.1,5382.8,5399.2,5404.4,5420.7,5429,5445.5,5451,5467.2,5469.8,5486.3,5494.8,5511.7,5519.5,5535.5,5542.9,5544.5,5546.7,5558.3,5566,5579.8,5584.6,5606.6,5623,5627.9,5648.9,5665.3,5670.8,5687.4,5707.1,5728.8,5729.3,5750.8,5762.3,5766,5768.2,5781.1,5783.9,5786.8,5801.8,5815.3,5822.7,5838.8,5847,5863.3,5876.5,5886.8,5898,5901.1,5904.1,5918.4,5929.5,5931.9,5934.8,5935.8,5936.6,5938.6,5946.9,5963.8,5966.8,5980,5985.4,6000,6011.5,6029.9,6038.6,6043.2,6065.8,6075.7,6081.4,6095.9,6105,6128.7,6151.4,6161.1,6175.3,6193.7,6203.3,6208.9,6213.3,6223,6227,6245.5,6255.9,6264.4,6265.9,6266.2,6277.4,6279.4,6292.4,6305,6319,6321.3,6332.2,6334.7,6350.4,6353.1,6363.7,6378.5,6394.3,6399.7,6407.8,6424,6426.1,6441.5,6447.1,6464.4,6470,6486.9,6497,6511.7,6516.1,6531.3,6542,6558.4,6569.6,6585,6595.9,6610,6620.9,6623.6,6635.1,6640.3,6650,6654.7,6662.9,6674.1,6693.8,6697.8,6702.2,6706.8,6711.6,6717.2,6726.1,6744.4,6753.9,6758.4,6766.3,6775,6791.6,6806.6,6815.9,6823,6828,6832.5,6835,6836.5,6850,6866.1,6874.7,6883.4,6886.8,6889.3,6908.5,6914.4,6930.5,6935.8,6946.6,6960.9,6963.3,6968.7,6984,6987.3,6993,7006.7,7022.7,7027.6,7036.7,7048.9,7053.6,7068.3,7079.4,7094.4,7099.6,7110,7117.1,7120,7137.1,7149.5,7171.1,7181.3,7198.1,7206.4,7209,7223.1,7233.5,7249.9,7258.2,7274.2,7280.3,7286.1,7296.4,7305.3,7328,7332.7,7337.7,7347.6,7362.9,7367.6,7372.4,7382.6,7387.4,7395.9,7406.7,7422.6,7427.9,7437.1,7445.7,7454.9,7478.8,7483.6,7493.4,7512.3,7521.3,7525.8,7530.5,7539.9,7544.8,7554.3,7558.8,7570.4,7573.5,7573.6,7578.3,7586.8,7592.7,7598.3,7614.2,7632.7,7641.5,7644,7654.1,7672.6,7680.8,7693.9,7699.3,7713.8,7717.4,7730.7,7742.1,7744.9,7756.3,7759.5,7771.2,7779.5,7786.6,7793.5,7796.2,7813.4,7821.8,7831.1,7847.2,7861.3,7863.1,7875.9,7880.9,7889.9,7904.7,7920.1,7922.4,7926.6,7932.1,7945.1,7950.4,7964,7982.8,7988.3,8002.4,8019.2,8027.4,8042,8046.8,8062.2,8064.6,8079.8,8083.5,8098.4,8100.5,8116.5,8119.1,8125.5,8132.8,8137.5,8145.8,8159,8160.5,8166.6,8173.9,8188.4,8197.5,8207.1,8212,8219.4,8234,8236.3,8238.8,8253.6,8258.6,8273.8,8276.3,8291.6,8299.2,8312.3,8324.9,8330.1,8335.3,8344.3,8359.3,8364.8,8380.8,8394.5,8408.1,8423.4,8430.7,8433.5,8448.3,8453.2,8462.4,8472.8,8478,8483.5,8489,8494.5,8510.3,8515.3,8520.4,8530.7,8540.9,8561.2,8566.2,8590.6,8614.8,8625,8639.7,8649,8654,8668.7,8678,8687.1,8691.9,8708.9,8712.1,8720.7,8741.1,8746.1,8755.6,8765.2,8770.1,8774.8,8779.7,8788,8790.5,8792,8804.5,8824.3,8826.5,8831.2,8843.8,8859,8861.7,8864.3,8871.9,8879.3,8884.3,8886.5,8893.2,8902,8904.6,8909.3,8918.6,8926.4,8934,8948.6,8962.8,8970,8975,8987.1,9001.1,9016.5,9018.9,9033.4,9035.7,9050.4,9060.2,9074.8,9089.8,9097.3,9100,9116.1,9124.9,9135.9,9149.1,9164.5,9172.1,9186.8,9201.9,9207,9221.3,9223.9,9238.6,9246.1,9262.1,9269.8,9272.5,9289.5,9302.6,9319.6,9336.6,9347.7,9362.3,9375.5,9381.2,9388.5,9396,9419.4,9442.6,9452.4,9473.2,9493.5,9498.6,9503.7,9513.5,9522,9542.7,9544.3,9544.9,9548.1,9551.9,9575.5,9581.1,9585.8,9590.5,9592.7,9601,9606.6,9618.6,9631.3,9640.6,9648.7,9652.8,9656.6,9667.8,9670.1,9673.7,9679.4,9686.7,9694.3,9705,9708.1,9719,9727,9739.4,9746.8,9752.3,9758.7,9771.2,9785.9,9794.3,9807.5,9813.2,9829.4,9834.9,9850.2,9856.1,9870.8,9881.5,9892.3,9899.6,9904.5,9907.2,9920.7,9930.5,9955.6,9969.9,9994.1,10003.6,10012.6,10032.2,10054.3,10066,10089.6,10104.1,10117.6,10125.4,10139.8,10162.8,10176.4,10176.7,10179.1,10190,10210.1,10229.6,10238.7,10242.8,10246.2,10247.1,10260.9,10275.1,10285.7,10303.2,10310.9,10316.8,10330.7,10333.2,10335.4,10342.2,10344.6,10360,10364.4,10379.2,10382.5,10384.6,10390.7,10392.2,10401.6,10404.2,10419.7,10427.6,10430.2,10435.4,10449.4,10453.8,10463.6,10469,10480.8,10484.6,10489,10497.9,10504.7,10514.3,10522,10530.7,10535.3,10544.7,10553.2,10563.3,10584.6,10589.7,10598.2,10616.1,10640.6,10663.4,10681.1,10702,10706.3,10726.6,10735.5,10754.2,10763.7,10784.3,10789.2,10810.7,10811,10813,10814.4,10824.9,10836.1,10846.3,10856.2,10871.8,10890.1,10897.3,10900,10910.7,10920.7,10935.5,10945.3,10960.5,10963,10979.9,10982.2,10987.1,10998.1,11003.1,11013.3,11031.6,11046.9,11049.5,11064.9,11070.8,11087.4,11094.2,11109,11113.7,11129.6,11140,11155.2,11163.6,11178.9,11181.6,11196.5,11203.3,11219.1,11231.9,11247.9,11258.2,11265.4,11281.8,11284.7,11299.7,11301.9,11313.5,11322,11335.3,11360,11363.3,11371.6,11376.2,11380.6,11385.2,11407.2,11411.3,11431.4,11444.6,11461.8,11485.1,11507.7,11515.9,11525.3,11550,11554,11559.4,11575,11598.7,11607.3,11610.6,11612.5,11614,11625.1,11639.5,11647.7,11655.6,11667.7,11684.5,11689.8,11692.4,11697,11709.3,11714.1,11726.8,11734.5,11749.5,11752,11768.2,11773.9,11787.9,11794.7,11797,11811.8,11816.2,11818.5,11833.3,11843.5,11848.4,11858.5,11871.8,11878.5,11882.9,11900,11911.7,11917.6,11920.6,11935.1,11936.9,11938.4,11940.3,11953.7,11956.4,11957.7,11958.1,11958.1,11958.5,11964.5,11970.2,11973.3,11988.2,12000.8,12002.9,12009.5,12018,12032.6,12041.4,12056,12058.2,12063.4,12068,12074.1,12089,12099,12101.3,12106.5,12115.3,12118,12132.3,12140.2,12154.6,12169.4,12174.2,12191.5,12200.4,12204.8,12216.4,12230,12244.1,12267,12271.2,12283.4,12303.1,12307.8,12311.7,12332,12349.8,12373.9,12387.6,12408.2,12416.6,12438.6,12441.9,12461,12484,12490.7,12491.6,12494.2,12505.8,12510.6,12533.7,12536.8,12558.1,12566.1,12575.8,12576.9,12579.8,12582.1,12584.8,12599,12614.9,12623,12629.9,12646.5,12657.6,12660.3,12668.8,12676.3,12686,12696.4,12707.9,12722.4,12730.4,12746.6,12756.3,12767.5,12773.8,12789.1,12793.9,12810,12820.3,12825.3,12833.3,12838.2,12844.8,12857.3,12861.7,12865.2,12869.5,12889.7,12897.6,12905.9,12921.8,12930.1,12952,12960.7,12977.7,12995.3,13012.8,13024.7,13027.8,13030.7,13032.3,13047,13066.5,13074.3,13076.6,13088.2,13104.8,13112,13123.2,13125.5,13133.1,13143,13150.1,13156.5,13162.9,13178.4,13189.3,13206,13208.6,13224.4,13229.2,13243.9,13248.5,13253.1,13263.2,13278.7,13287.8,13296.1,13304.2,13308.5,13317.2,13326,13343.4,13356.3,13372.6,13393.3,13401.1,13405.3,13408.4,13418.8,13436.9,13441.5,13443.8,13451.8,13456.4,13471.1,13479.2,13481,13483.5,13493.1,13513.1,13523.9,13541.4,13544.1,13557.8,13567.8,13575,13585.7,13590,13600,13603.4,13613.2,13621.7,13624.9,13628.3,13638.3,13655.7,13660.3,13674.2,13683.6,13700.8,13708.8,13732,13741.7,13743.2,13755.6,13764,13779.6,13789.2,13800.3,13813,13826.8,13842.2,13850.7,13858.5,13865.8,13876.2,13896.8,13915.1,13924.6,13947.5,13955.1,13959,13963.4,13967.6,13988.6,13999.9,14004.1,14023.1,14037.2,14055.8,14076.4,14083.2,14102.8,14115.3,14129.4,14143.1,14154.7,14162.1,14183.1,14190.6,14210.7,14218.7,14239,14246.7,14270.3,14292.6,14296.6,14309.2,14318.9],"time":[0,5,6,8,9,12,14,15,19,20,21,23,26,27,32,36,37,43,46,48,49,52,55,58,62,68,71,74,75,78,84,87,92,96,101,106,112,114,119,123,125,127,128,131,137,140,144,147,149,153,156,162,164,170,176,179,183,189,190,191,197,198,203,209,210,211,214,216,222,223,229,232,234,238,244,248,252,257,262,268,269,275,276,279,285,288,293,294,296,300,301,307,308,311,317,318,322,326,330,335,341,342,344,350,351,357,363,369,370,376,377,379,392,393,397,399,404,410,411,417,423,424,427,431,433,439,440,444,448,449,455,457,459,464,480,481,485,491,492,497,503,505,511,512,516,520,526,528,530,536,539,540,543,549,552,558,560,566,568,572,578,584,588,594,597,603,605,609,612,618,619,625,627,633,635,641,644,650,652,655,660,666,668,672,678,679,685,686,692,696,702,703,709,710,716,719,723,727,729,731,732,735,740,744,745,747,748,752,753,759,760,761,766,770,773,778,782,786,788,789,792,793,795,800,803,808,810,815,819,820,822,827,831,836,838,842,844,846,848,852,855,857,858,859,860,861,863,865,866,872,877,881,883,889,891,893,899,900,902,905,907,911,914,915,921,922,924,926,928,934,936,940,943,949,952,955,959,965,969,975,978,982,983,985,991,997,1001,1007,1010,1016,1020,1026,1030,1035,1039,1043,1044,1045,1051,1052,1055,1060,1061,1062,1064,1067,1068,1070,1073,1075,1077,1082,1085,1086,1088,1089,1093,1095,1096,1097,1099,1100,1101,1105,1108,1109,1112,1114,1119,1123,1127,1129,1131,1135,1139,1140,1142,1145,1148,1149,1151,1157,1163,1167,1170,1174,1180,1182,1185,1189,1190,1195,1200,1204,1208,1213,1215,1216,1221,1224,1225,1229,1231,1232,1235,1241,1242,1243,1249,1252,1258,1259,1261,1263,1264,1267,1270,1272,1274,1276,1277,1282,1283,1288,1289,1293,1295,1296,1298,1301,1303,1307,1312,1318,1322,1327,1328,1334,1336,1342,1344,1350,1356,1362,1363,1369,1371,1377,1379,1384,1390,1392,1396,1398,1403,1408,1411,1412,1414,1416,1418,1420,1422,1423,1425,1426,1428,1429,1430,1432,1434,1435,1436,1437,1438,1441,1442,1444,1445,1446,1449,1450,1455,1456,1460,1464,1468,1469,1470,1471,1472,1473,1474,1476,1481,1484,1489,1490,1491,1493,1495,1497,1499,1500,1501,1502,1505,1510,1513,1514,1515,1516,1519,1524,1530,1532,1537,1542,1545,1551,1555,1559,1560,1566,1570,1572,1574,1580,1582,1587,1589,1593,1596,1602,1605,1608,1613,1618,1620,1622,1628,1631,1637,1640,1646,1649,1655,1657,1661,1665,1671,1672,1675,1677,1682,1687,1689,1695,1698,1704,1707,1713,1716,1722,1723,1729,1734,1740,1742,1748,1749,1750,1751,1753,1754,1759,1760,1763,1764,1768,1774,1777,1780,1782,1787,1791,1792,1795,1801,1803,1804,1809,1815,1816,1822,1824,1830,1831,1837,1839,1845,1848,1854,1856,1862,1863,1869,1872,1878,1881,1887,1891,1892,1893,1897,1900,1904,1905,1909,1912,1913,1917,1920,1921,1924,1928,1933,1934,1939,1941,1942,1944,1949,1950,1951,1957,1962,1965,1971,1974,1980,1985,1989,1993,1994,1995,2000,2004,2005,2007,2008,2009,2011,2015,2021,2022,2027,2029,2034,2037,2041,2043,2044,2049,2051,2052,2055,2057,2062,2067,2069,2072,2076,2078,2079,2080,2084,2087,2091,2093,2095,2096,2097,2103,2104,2110,2116,2122,2123,2128,2129,2135,2136,2140,2146,2152,2154,2157,2163,2164,2170,2172,2178,2180,2186,2190,2196,2198,2204,2208,2214,2218,2224,2228,2234,2239,2240,2244,2245,2247,2248,2250,2252,2256,2257,2258,2259,2260,2261,2263,2267,2269,2270,2272,2274,2277,2280,2282,2284,2285,2286,2287,2289,2293,2296,2298,2302,2304,2305,2311,2313,2319,2321,2326,2332,2333,2335,2341,2342,2344,2349,2355,2357,2360,2364,2366,2372,2376,2382,2384,2388,2391,2392,2398,2402,2408,2411,2417,2420,2421,2427,2431,2437,2440,2446,2448,2450,2453,2455,2460,2461,2462,2464,2467,2468,2469,2471,2472,2474,2476,2479,2480,2482,2484,2486,2491,2492,2494,2498,2500,2501,2502,2504,2505,2507,2508,2511,2513,2514,2516,2518,2519,2520,2523,2527,2530,2532,2535,2541,2544,2548,2550,2556,2558,2563,2567,2568,2572,2573,2578,2582,2585,2588,2589,2595,2598,2602,2608,2614,2615,2620,2622,2625,2631,2637,2638,2640,2642,2647,2649,2655,2661,2663,2668,2674,2677,2683,2685,2691,2692,2698,2700,2706,2707,2713,2714,2717,2720,2722,2725,2731,2732,2735,2738,2744,2748,2752,2754,2757,2763,2764,2765,2771,2773,2779,2780,2786,2789,2794,2799,2801,2803,2807,2813,2815,2821,2826,2831,2837,2840,2841,2845,2846,2848,2850,2851,2852,2853,2854,2857,2858,2859,2861,2863,2867,2868,2873,2878,2880,2883,2885,2886,2889,2891,2893,2894,2898,2900,2903,2907,2908,2910,2912,2913,2914,2915,2917,2919,2920,2924,2930,2931,2933,2938,2944,2945,2946,2949,2952,2954,2955,2958,2962,2963,2965,2969,2972,2975,2981,2986,2989,2991,2996,3002,3008,3009,3015,3016,3022,3026,3032,3038,3041,3042,3048,3051,3055,3060,3066,3069,3075,3081,3083,3089,3090,3096,3099,3105,3108,3109,3115,3120,3126,3132,3136,3141,3147,3149,3151,3153,3158,3163,3165,3169,3173,3174,3175,3177,3179,3184,3185,3186,3188,3189,3193,3194,3195,3197,3199,3202,3204,3208,3212,3215,3218,3220,3222,3226,3227,3228,3230,3233,3236,3240,3241,3245,3248,3253,3256,3258,3260,3264,3270,3273,3278,3280,3286,3288,3294,3296,3302,3306,3310,3313,3315,3316,3319,3321,3326,3329,3334,3336,3338,3342,3347,3350,3355,3358,3361,3363,3366,3371,3375,3376,3377,3380,3384,3388,3390,3391,3393,3394,3399,3404,3408,3414,3417,3419,3424,3425,3426,3429,3430,3436,3438,3444,3445,3446,3449,3450,3455,3456,3462,3465,3466,3468,3474,3476,3481,3483,3489,3491,3493,3497,3500,3503,3505,3507,3508,3510,3512,3514,3519,3520,3522,3526,3531,3536,3540,3545,3546,3551,3553,3559,3562,3566,3567,3573,3574,3576,3577,3582,3585,3588,3591,3595,3601,3604,3605,3609,3612,3618,3622,3628,3629,3635,3636,3638,3642,3644,3648,3654,3660,3661,3667,3669,3675,3678,3684,3686,3692,3696,3702,3705,3711,3712,3718,3721,3727,3732,3738,3742,3745,3751,3752,3758,3759,3763,3765,3768,3773,3774,3776,3777,3778,3779,3784,3785,3790,3793,3797,3802,3807,3809,3811,3817,3818,3821,3825,3830,3832,3833,3835,3836,3841,3846,3849,3852,3856,3862,3864,3865,3867,3872,3874,3879,3882,3888,3889,3895,3897,3902,3905,3906,3912,3914,3915,3921,3926,3928,3932,3937,3940,3942,3948,3952,3954,3955,3960,3961,3962,3963,3968,3969,3971,3972,3978,3981,3983,3985,3986,3991,3996,3997,4000,4003,4009,4013,4019,4020,4022,4024,4027,4033,4037,4038,4040,4043,4044,4048,4050,4053,4056,4057,4061,4063,4064,4067,4070,4073,4078,4079,4082,4087,4088,4089,4094,4098,4104,4107,4112,4114,4119,4120,4125,4131,4133,4134,4136,4139,4140,4145,4146,4151,4153,4156,4158,4160,4161,4162,4167,4173,4176,4178,4184,4188,4189,4192,4195,4199,4203,4208,4214,4217,4223,4227,4232,4235,4241,4243,4249,4253,4255,4258,4260,4262,4265,4266,4267,4268,4273,4275,4277,4281,4283,4288,4290,4294,4298,4302,4305,4306,4308,4309,4312,4316,4319,4321,4325,4331,4334,4339,4340,4343,4347,4350,4353,4356,4362,4366,4372,4373,4379,4381,4387,4389,4391,4395,4401,4405,4408,4410,4411,4413,4415,4419,4422,4426,4431,4433,4434,4435,4438,4443,4446,4447,4449,4450,4453,4456,4458,4459,4462,4468,4472,4478,4479,4484,4488,4491,4495,4497,4501,4502,4506,4509,4510,4511,4514,4518,4519,4522,4524,4528,4530,4535,4539,4540,4543,4547,4552,4555,4559,4564,4570,4576,4579,4582,4585,4588,4593,4597,4599,4604,4606,4607,4608,4609,4614,4617,4618,4622,4625,4630,4635,4637,4642,4645,4649,4653,4656,4658,4663,4665,4670,4672,4677,4679,4685,4690,4691,4694,4697]}}